FPGA_Unit/src/rtl/esp_interface.v
//
// esp_interface.v
// 
// SPI slave module for receiving data from ESP32 DevKit
// Mode 0: CPOL=0, CPHA=0 (sample on rising edge, shift on falling edge)
//

module esp_interface (
    input  wire        clk,          // System clock (27 MHz)
    input  wire        rst_n,        // Active-low reset
    
    // SPI interface
    input  wire        esp_mosi,     // Master Out Slave In
    output reg         esp_miso,     // Master In Slave Out
    input  wire        esp_sclk,     // SPI clock from master
    input  wire        esp_cs_n,     // Chip select (active low)
    
    // Parallel data interface
    output reg  [7:0]  rx_data,      // Received byte
    output reg         rx_valid,     // Data valid strobe
    input  wire        rx_ready      // Ready for next byte
);

    //==========================================================================
    // Internal signals
    //==========================================================================
    
    // Synchronize SPI signals to system clock domain
    reg [2:0] sclk_sync;
    reg [2:0] cs_sync;
    reg [1:0] mosi_sync;
    
    wire sclk_rising;
    wire sclk_falling;
    wire cs_active;
    
    // Shift register
    reg [7:0] shift_reg;
    reg [2:0] bit_count;
    
    // State
    reg       byte_ready;
    
    //==========================================================================
    // Synchronize SPI signals (avoid metastability)
    //==========================================================================
    
    always @(posedge clk or negedge rst_n) begin
        if (!rst_n) begin
            sclk_sync <= 3'b000;
            cs_sync   <= 3'b111;
            mosi_sync <= 2'b00;
        end
        else begin
            sclk_sync <= {sclk_sync[1:0], esp_sclk};
            cs_sync   <= {cs_sync[1:0], esp_cs_n};
            mosi_sync <= {mosi_sync[0], esp_mosi};
        end
    end
    
    // Edge detection
    assign sclk_rising  = (sclk_sync[2:1] == 2'b01);
    assign sclk_falling = (sclk_sync[2:1] == 2'b10);
    assign cs_active    = !cs_sync[2];  // Active low
    
    //==========================================================================
    // SPI Mode 0: Sample on rising edge, shift on falling edge
    //==========================================================================
    
    always @(posedge clk or negedge rst_n) begin
        if (!rst_n) begin
            shift_reg  <= 8'h00;
            bit_count  <= 3'd0;
            byte_ready <= 1'b0;
        end
        else begin
            byte_ready <= 1'b0;  // Default: clear strobe
           
            if (!cs_active) begin
                // CS deasserted - reset
                bit_count <= 3'd0;
                shift_reg <= 8'h00;
            end
            else if (sclk_rising) begin
                // Sample MOSI on rising edge
                shift_reg <= {shift_reg[6:0], mosi_sync[1]};
                bit_count <= bit_count + 1'b1;
                
                // After 8 bits, byte is complete
                if (bit_count == 3'd7) begin
                    byte_ready <= 1'b1;
                    bit_count  <= 3'd0;
                end
            end
        end
    end
    
    //==========================================================================
    // Output received byte with valid strobe
    //==========================================================================
    
    always @(posedge clk or negedge rst_n) begin
        if (!rst_n) begin
            rx_data  <= 8'h00;
            rx_valid <= 1'b0;
        end
        else begin
            if (byte_ready) begin
                rx_data  <= {shift_reg[6:0], mosi_sync[1]};  // Include last bit
                rx_valid <= 1'b1;
            end
            else begin
                rx_valid <= 1'b0;
            end
        end
    end
    
    //==========================================================================
    // MISO output (for now, just send dummy data)
    // TODO: Implement proper response when needed
    //==========================================================================
    
    always @(posedge clk or negedge rst_n) begin
        if (!rst_n) begin
            esp_miso <= 1'b0;
        end
        else begin
            if (!cs_active) begin
                esp_miso  <= 1'b0;
            end
            else if (sclk_falling) begin
                // Shift out dummy data on falling edge
                esp_miso <= 1'b0;  // TODO: shift out actual response
            end
        end
    end

endmodule

fpga/sim/esp_interface_tb.v
`timescale 1ns / 1ps

module esp_interface_tb;

        //==========================================================================
        // Parameters
        //==========================================================================

        localparam CLK_PERIOD = 37;  // 27MHz = ~37ns period
        localparam SPI_PERIOD = 200; // 5MHz SPI clock (slower than sys_clk)

        //==========================================================================
        // Signals
        //==========================================================================

        // System
        reg clk;
        reg rst_n;

        // SPI interface (directly from testbench to DUT)
        reg tb_mosi;
        wire tb_miso;
        reg tb_sclk;
        reg tb_cs_n;

        // Output from DUT
        wire [7 : 0] rx_data;
        wire rx_valid;
        reg rx_ready;

        // Test tracking
        integer bytes_received;
        integer errors;
        reg [7 : 0] expected_data;

        //==========================================================================
        // DUT instantiation
        //==========================================================================

        esp_interface dut(.clk(clk),
                          .rst_n(rst_n),
                          .esp_mosi(tb_mosi),
                          .esp_miso(tb_miso),
                          .esp_sclk(tb_sclk),
                          .esp_cs_n(tb_cs_n),
                          .rx_data(rx_data),
                          .rx_valid(rx_valid),
                          .rx_ready(rx_ready));

        //==========================================================================
        // Clock generation
        //==========================================================================

        initial begin
                clk = 0;
                forever
                        #(CLK_PERIOD / 2) clk = ~clk;
        end

        //==========================================================================
        // SPI Master tasks (simulates ESP32)
        //==========================================================================

        // Send a single byte over SPI (MSB first, Mode 0)
        task spi_send_byte;
                input [7 : 0] data;
                integer i;
                begin
                        for (i = 7; i >= 0; i = i - 1) begin
                                tb_mosi = data[i];
                                #(SPI_PERIOD / 2);
                                tb_sclk = 1; // Rising edge - DUT samples
                                #(SPI_PERIOD / 2);
                                tb_sclk = 0; // Falling edge
                        end
                end
        endtask

        // Send multiple bytes (like a DMA transfer)
        task spi_send_burst;
                input [7 : 0] start_val;
                input integer num_bytes;
                integer i;
                begin
                        tb_cs_n = 0; // Assert CS
                        #(SPI_PERIOD);

                        for (i = 0; i < num_bytes; i = i + 1) begin
                                spi_send_byte(start_val + i);
                                #(SPI_PERIOD / 2); // Small gap between bytes
                        end

                        #(SPI_PERIOD);
                        tb_cs_n = 1; // Deassert CS
                end
        endtask

        //==========================================================================
        // Monitor received data
        //==========================================================================

        always @(posedge clk) begin
                if (rx_valid) begin
                        $display(
                            "[%0t] RX byte: 0x%02X (expected: 0x%02X) %s",
                            $time, rx_data, expected_data,
                            (rx_data == expected_data) ? "OK" : "MISMATCH!");

                        if (rx_data !== expected_data) begin
                                errors = errors + 1;
                        end

                        bytes_received = bytes_received + 1;
                        expected_data = expected_data + 1;
                end
        end

        //==========================================================================
        // Main test sequence
        //==========================================================================

        initial begin
                // Setup waveform dump
                $dumpfile("esp_interface_tb.vcd");
                $dumpvars(0, esp_interface_tb);

                // Initialize
                rst_n = 0;
                tb_mosi = 0;
                tb_sclk = 0;
                tb_cs_n = 1;
                rx_ready = 1;
                bytes_received = 0;
                errors = 0;
                expected_data = 8'hAA;

                // Reset
                #(CLK_PERIOD * 10);
                rst_n = 1;
                #(CLK_PERIOD * 10);

                $display("===========================================");
                $display("ESP Interface Testbench Starting");
                $display("===========================================");

                //----------------------------------------------------------------------
                // Test 1: Single byte transfer
                //----------------------------------------------------------------------
                $display("\n[TEST 1] Single byte transfer");
                expected_data = 8'hAA;
                tb_cs_n = 0;
                #(SPI_PERIOD);
                spi_send_byte(8'hAA);
                #(SPI_PERIOD * 2);
                tb_cs_n = 1;
                #(CLK_PERIOD * 20);

                //----------------------------------------------------------------------
                // Test 2: Multiple bytes (simulating image data)
                //----------------------------------------------------------------------
                $display("\n[TEST 2] Burst transfer (16 bytes)");
                expected_data = 8'h00;
                spi_send_burst(8'h00, 16);
                #(CLK_PERIOD * 50);

                //----------------------------------------------------------------------
                // Test 3: Fast burst (stress test)
                //----------------------------------------------------------------------
                $display("\n[TEST 3] Fast burst (64 bytes)");
                expected_data = 8'h40;
                spi_send_burst(8'h40, 64);
                #(CLK_PERIOD * 100);

                //----------------------------------------------------------------------
                // Test 4: CS deassert mid-byte (error recovery)
                //----------------------------------------------------------------------
                $display("\n[TEST 4] CS deassert mid-byte (should recover)");
                tb_cs_n = 0;
                #(SPI_PERIOD);
                tb_mosi = 1;
                #(SPI_PERIOD / 2);
                tb_sclk = 1;
                #(SPI_PERIOD / 2);
                tb_sclk = 0;
                #(SPI_PERIOD / 2);
                tb_sclk = 1;
                #(SPI_PERIOD / 2);
                tb_sclk = 0;
                #(SPI_PERIOD / 2);
                tb_sclk = 1;
                #(SPI_PERIOD / 2);
                tb_sclk = 0;
                // Deassert CS after only 3 bits
                tb_cs_n = 1;
                #(CLK_PERIOD * 20);

                // Now send a clean byte - should work
                $display("  Sending clean byte after glitch...");
                expected_data = 8'h55;
                tb_cs_n = 0;
                #(SPI_PERIOD);
                spi_send_byte(8'h55);
                #(SPI_PERIOD * 2);
                tb_cs_n = 1;
                #(CLK_PERIOD * 20);

                //----------------------------------------------------------------------
                // Results
                //----------------------------------------------------------------------
                #(CLK_PERIOD * 50);

                $display("\n===========================================");
                $display("Test Complete");
                $display("  Bytes received: %0d", bytes_received);
                $display("  Errors: %0d", errors);
                $display("===========================================");

                if (errors == 0)
                        $display("*** PASS ***");
                else
                        $display("*** FAIL ***");

                $finish;
        end

        //==========================================================================
        // Timeout watchdog
        //==========================================================================

        initial begin
                #(1000000); // 1ms timeout
                $display("ERROR: Testbench timeout!");
                $finish;
        end
endmodule

FPGA_Unit/src/esp_interface_tb.vcd
$date
	Thu Dec  4 03:57:52 2025
$end
$version
	Icarus Verilog
$end
$timescale
	1ps
$end
$scope module esp_interface_tb $end
$var wire 1 ! tb_miso $end
$var wire 1 " rx_valid $end
$var wire 8 # rx_data [7:0] $end
$var parameter 32 $ CLK_PERIOD $end
$var parameter 32 % SPI_PERIOD $end
$var reg 1 & clk $end
$var reg 8 ' expected_data [7:0] $end
$var reg 1 ( rst_n $end
$var reg 1 ) rx_ready $end
$var reg 1 * tb_cs_n $end
$var reg 1 + tb_mosi $end
$var reg 1 , tb_sclk $end
$var integer 32 - bytes_received [31:0] $end
$var integer 32 . errors [31:0] $end
$scope module dut $end
$var wire 1 & clk $end
$var wire 1 * esp_cs_n $end
$var wire 1 + esp_mosi $end
$var wire 1 , esp_sclk $end
$var wire 1 ( rst_n $end
$var wire 1 ) rx_ready $end
$var wire 1 / sclk_rising $end
$var wire 1 0 sclk_falling $end
$var wire 1 1 cs_active $end
$var reg 3 2 bit_count [2:0] $end
$var reg 1 3 byte_ready $end
$var reg 3 4 cs_sync [2:0] $end
$var reg 1 ! esp_miso $end
$var reg 2 5 mosi_sync [1:0] $end
$var reg 8 6 rx_data [7:0] $end
$var reg 1 " rx_valid $end
$var reg 3 7 sclk_sync [2:0] $end
$var reg 8 8 shift_reg [7:0] $end
$upscope $end
$scope task spi_send_burst $end
$var reg 8 9 start_val [7:0] $end
$var integer 32 : i [31:0] $end
$var integer 32 ; num_bytes [31:0] $end
$upscope $end
$scope task spi_send_byte $end
$var reg 8 < data [7:0] $end
$var integer 32 = i [31:0] $end
$upscope $end
$upscope $end
$enddefinitions $end
$comment Show the parameter values. $end
$dumpall
b11001000 %
b100101 $
$end
#0
$dumpvars
bx =
bx <
bx ;
bx :
bx 9
b0 8
b0 7
b0 6
b0 5
b111 4
03
b0 2
01
00
0/
b0 .
b0 -
0,
0+
1*
1)
0(
b10101010 '
0&
b0 #
0"
0!
$end
#18000
1&
#36000
0&
#54000
1&
#72000
0&
#90000
1&
#108000
0&
#126000
1&
#144000
0&
#162000
1&
#180000
0&
#198000
1&
#216000
0&
#234000
1&
#252000
0&
#270000
1&
#288000
0&
#306000
1&
#324000
0&
#342000
1&
#360000
0&
#370000
1(
#378000
1&
#396000
0&
#414000
1&
#432000
0&
#450000
1&
#468000
0&
#486000
1&
#504000
0&
#522000
1&
#540000
0&
#558000
1&
#576000
0&
#594000
1&
#612000
0&
#630000
1&
#648000
0&
#666000
1&
#684000
0&
#702000
1&
#720000
0&
#738000
1&
#740000
0*
#756000
0&
#774000
b110 4
1&
#792000
0&
#810000
b100 4
1&
#828000
0&
#846000
11
b0 4
1&
#864000
0&
#882000
1&
#900000
0&
#918000
1&
#936000
0&
#940000
1+
b111 =
b10101010 <
#954000
b1 5
1&
#972000
0&
#990000
b11 5
1&
#1008000
0&
#1026000
1&
#1040000
1,
#1044000
0&
#1062000
b1 7
1&
#1080000
0&
#1098000
1/
b11 7
1&
#1116000
0&
#1134000
0/
b111 7
b1 2
b1 8
1&
#1140000
0+
b110 =
0,
#1152000
0&
#1170000
b10 5
b110 7
1&
#1188000
0&
#1206000
10
b0 5
b100 7
1&
#1224000
0&
#1240000
1,
#1242000
00
b1 7
1&
#1260000
0&
#1278000
1/
b11 7
1&
#1296000
0&
#1314000
0/
b10 2
b10 8
b111 7
1&
#1332000
0&
#1340000
1+
b101 =
0,
#1350000
b1 5
b110 7
1&
#1368000
0&
#1386000
10
b11 5
b100 7
1&
#1404000
0&
#1422000
00
b0 7
1&
#1440000
0&
1,
#1458000
b1 7
1&
#1476000
0&
#1494000
1/
b11 7
1&
#1512000
0&
#1530000
0/
b11 2
b101 8
b111 7
1&
#1540000
0+
b100 =
0,
#1548000
0&
#1566000
b10 5
b110 7
1&
#1584000
0&
#1602000
10
b0 5
b100 7
1&
#1620000
0&
#1638000
00
b0 7
1&
#1640000
1,
#1656000
0&
#1674000
b1 7
1&
#1692000
0&
#1710000
1/
b11 7
1&
#1728000
0&
#1740000
1+
b11 =
0,
#1746000
0/
b100 2
b1010 8
b1 5
b110 7
1&
#1764000
0&
#1782000
10
b11 5
b100 7
1&
#1800000
0&
#1818000
00
b0 7
1&
#1836000
0&
#1840000
1,
#1854000
b1 7
1&
#1872000
0&
#1890000
1/
b11 7
1&
#1908000
0&
#1926000
0/
b111 7
b101 2
b10101 8
1&
#1940000
0+
b10 =
0,
#1944000
0&
#1962000
b10 5
b110 7
1&
#1980000
0&
#1998000
10
b0 5
b100 7
1&
#2016000
0&
#2034000
00
b0 7
1&
#2040000
1,
#2052000
0&
#2070000
b1 7
1&
#2088000
0&
#2106000
1/
b11 7
1&
#2124000
0&
#2140000
1+
b1 =
0,
#2142000
0/
b1 5
b110 7
b110 2
b101010 8
1&
#2160000
0&
#2178000
10
b11 5
b100 7
1&
#2196000
0&
#2214000
00
b0 7
1&
#2232000
0&
#2240000
1,
#2250000
b1 7
1&
#2268000
0&
#2286000
1/
b11 7
1&
#2304000
0&
#2322000
0/
b111 2
b1010101 8
b111 7
1&
#2340000
0&
0+
b0 =
0,
#2358000
b10 5
b110 7
1&
#2376000
0&
#2394000
10
b0 5
b100 7
1&
#2412000
0&
#2430000
00
b0 7
1&
#2440000
1,
#2448000
0&
#2466000
b1 7
1&
#2484000
0&
#2502000
1/
b11 7
1&
#2520000
0&
#2538000
0/
13
b0 2
b10101010 8
b111 7
1&
#2540000
b11111111111111111111111111111111 =
0,
#2556000
0&
#2574000
b110 7
03
1"
b1010100 #
b1010100 6
1&
#2592000
0&
#2610000
10
0"
b100 7
b10101011 '
b1 -
b1 .
1&
#2628000
0&
#2646000
00
b0 7
1&
#2664000
0&
#2682000
1&
#2700000
0&
#2718000
1&
#2736000
0&
#2754000
1&
#2772000
0&
#2790000
1&
#2808000
0&
#2826000
1&
#2844000
0&
#2862000
1&
#2880000
0&
#2898000
1&
#2916000
0&
#2934000
1&
#2940000
1*
#2952000
0&
#2970000
b1 4
1&
#2988000
0&
#3006000
b11 4
1&
#3024000
0&
#3042000
01
b111 4
1&
#3060000
0&
#3078000
b0 8
1&
#3096000
0&
#3114000
1&
#3132000
0&
#3150000
1&
#3168000
0&
#3186000
1&
#3204000
0&
#3222000
1&
#3240000
0&
#3258000
1&
#3276000
0&
#3294000
1&
#3312000
0&
#3330000
1&
#3348000
0&
#3366000
1&
#3384000
0&
#3402000
1&
#3420000
0&
#3438000
1&
#3456000
0&
#3474000
1&
#3492000
0&
#3510000
1&
#3528000
0&
#3546000
1&
#3564000
0&
#3582000
1&
#3600000
0&
#3618000
1&
#3636000
0&
#3654000
1&
#3672000
0&
#3680000
0*
b10000 ;
b0 9
b0 '
#3690000
b110 4
1&
#3708000
0&
#3726000
b100 4
1&
#3744000
0&
#3762000
11
b0 4
1&
#3780000
0&
#3798000
1&
#3816000
0&
#3834000
1&
#3852000
0&
#3870000
1&
#3880000
b111 =
b0 <
b0 :
#3888000
0&
#3906000
1&
#3924000
0&
#3942000
1&
#3960000
0&
#3978000
1&
#3980000
1,
#3996000
0&
#4014000
b1 7
1&
#4032000
0&
#4050000
1/
b11 7
1&
#4068000
0&
#4080000
b110 =
0,
#4086000
0/
b110 7
b1 2
1&
#4104000
0&
#4122000
10
b100 7
1&
#4140000
0&
#4158000
00
b0 7
1&
#4176000
0&
#4180000
1,
#4194000
b1 7
1&
#4212000
0&
#4230000
1/
b11 7
1&
#4248000
0&
#4266000
0/
b10 2
b111 7
1&
#4280000
b101 =
0,
#4284000
0&
#4302000
b110 7
1&
#4320000
0&
#4338000
10
b100 7
1&
#4356000
0&
#4374000
00
b0 7
1&
#4380000
1,
#4392000
0&
#4410000
b1 7
1&
#4428000
0&
#4446000
1/
b11 7
1&
#4464000
0&
#4480000
b100 =
0,
#4482000
0/
b11 2
b110 7
1&
#4500000
0&
#4518000
10
b100 7
1&
#4536000
0&
#4554000
00
b0 7
1&
#4572000
0&
#4580000
1,
#4590000
b1 7
1&
#4608000
0&
#4626000
1/
b11 7
1&
#4644000
0&
#4662000
0/
b111 7
b100 2
1&
#4680000
0&
b11 =
0,
#4698000
b110 7
1&
#4716000
0&
#4734000
10
b100 7
1&
#4752000
0&
#4770000
00
b0 7
1&
#4780000
1,
#4788000
0&
#4806000
b1 7
1&
#4824000
0&
#4842000
1/
b11 7
1&
#4860000
0&
#4878000
0/
b111 7
b101 2
1&
#4880000
b10 =
0,
#4896000
0&
#4914000
b110 7
1&
#4932000
0&
#4950000
10
b100 7
1&
#4968000
0&
#4980000
1,
#4986000
00
b1 7
1&
#5004000
0&
#5022000
1/
b11 7
1&
#5040000
0&
#5058000
0/
b110 2
b111 7
1&
#5076000
0&
#5080000
b1 =
0,
#5094000
b110 7
1&
#5112000
0&
#5130000
10
b100 7
1&
#5148000
0&
#5166000
00
b0 7
1&
#5180000
1,
#5184000
0&
#5202000
b1 7
1&
#5220000
0&
#5238000
1/
b11 7
1&
#5256000
0&
#5274000
0/
b111 2
b111 7
1&
#5280000
b0 =
0,
#5292000
0&
#5310000
b110 7
1&
#5328000
0&
#5346000
10
b100 7
1&
#5364000
0&
#5380000
1,
#5382000
00
b1 7
1&
#5400000
0&
#5418000
1/
b11 7
1&
#5436000
0&
#5454000
0/
b111 7
13
b0 2
1&
#5472000
0&
#5480000
b11111111111111111111111111111111 =
0,
#5490000
1"
b0 #
b0 6
03
b110 7
1&
#5508000
0&
#5526000
10
b100 7
0"
b1 '
b10 -
1&
#5544000
0&
#5562000
00
b0 7
1&
#5580000
0&
b111 =
b1 <
b1 :
#5598000
1&
#5616000
0&
#5634000
1&
#5652000
0&
#5670000
1&
#5680000
1,
#5688000
0&
#5706000
b1 7
1&
#5724000
0&
#5742000
1/
b11 7
1&
#5760000
0&
#5778000
0/
b1 2
b111 7
1&
#5780000
b110 =
0,
#5796000
0&
#5814000
b110 7
1&
#5832000
0&
#5850000
10
b100 7
1&
#5868000
0&
#5880000
1,
#5886000
00
b1 7
1&
#5904000
0&
#5922000
1/
b11 7
1&
#5940000
0&
#5958000
0/
b111 7
b10 2
1&
#5976000
0&
#5980000
b101 =
0,
#5994000
b110 7
1&
#6012000
0&
#6030000
10
b100 7
1&
#6048000
0&
#6066000
00
b0 7
1&
#6080000
1,
#6084000
0&
#6102000
b1 7
1&
#6120000
0&
#6138000
1/
b11 7
1&
#6156000
0&
#6174000
0/
b111 7
b11 2
1&
#6180000
b100 =
0,
#6192000
0&
#6210000
b110 7
1&
#6228000
0&
#6246000
10
b100 7
1&
#6264000
0&
#6280000
1,
#6282000
00
b1 7
1&
#6300000
0&
#6318000
1/
b11 7
1&
#6336000
0&
#6354000
0/
b100 2
b111 7
1&
#6372000
0&
#6380000
b11 =
0,
#6390000
b110 7
1&
#6408000
0&
#6426000
10
b100 7
1&
#6444000
0&
#6462000
00
b0 7
1&
#6480000
0&
1,
#6498000
b1 7
1&
#6516000
0&
#6534000
1/
b11 7
1&
#6552000
0&
#6570000
0/
b101 2
b111 7
1&
#6580000
b10 =
0,
#6588000
0&
#6606000
b110 7
1&
#6624000
0&
#6642000
10
b100 7
1&
#6660000
0&
#6678000
00
b0 7
1&
#6680000
1,
#6696000
0&
#6714000
b1 7
1&
#6732000
0&
#6750000
1/
b11 7
1&
#6768000
0&
#6780000
b1 =
0,
#6786000
0/
b110 2
b110 7
1&
#6804000
0&
#6822000
10
b100 7
1&
#6840000
0&
#6858000
00
b0 7
1&
#6876000
0&
#6880000
1,
#6894000
b1 7
1&
#6912000
0&
#6930000
1/
b11 7
1&
#6948000
0&
#6966000
0/
b111 7
b111 2
1&
#6980000
1+
b0 =
0,
#6984000
0&
#7002000
b1 5
b110 7
1&
#7020000
0&
#7038000
10
b11 5
b100 7
1&
#7056000
0&
#7074000
00
b0 7
1&
#7080000
1,
#7092000
0&
#7110000
b1 7
1&
#7128000
0&
#7146000
1/
b11 7
1&
#7164000
0&
#7180000
b11111111111111111111111111111111 =
0,
#7182000
0/
b110 7
13
b0 2
b1 8
1&
#7200000
0&
#7218000
10
1"
b11 #
b11 6
03
b100 7
1&
#7236000
0&
#7254000
00
b0 7
0"
b10 '
b11 -
b10 .
1&
#7272000
0&
#7280000
0+
b111 =
b10 <
b10 :
#7290000
b10 5
1&
#7308000
0&
#7326000
b0 5
1&
#7344000
0&
#7362000
1&
#7380000
0&
1,
#7398000
b1 7
1&
#7416000
0&
#7434000
1/
b11 7
1&
#7452000
0&
#7470000
0/
b111 7
b1 2
b10 8
1&
#7480000
b110 =
0,
#7488000
0&
#7506000
b110 7
1&
#7524000
0&
#7542000
10
b100 7
1&
#7560000
0&
#7578000
00
b0 7
1&
#7580000
1,
#7596000
0&
#7614000
b1 7
1&
#7632000
0&
#7650000
1/
b11 7
1&
#7668000
0&
#7680000
b101 =
0,
#7686000
0/
b110 7
b10 2
b100 8
1&
#7704000
0&
#7722000
10
b100 7
1&
#7740000
0&
#7758000
00
b0 7
1&
#7776000
0&
#7780000
1,
#7794000
b1 7
1&
#7812000
0&
#7830000
1/
b11 7
1&
#7848000
0&
#7866000
0/
b11 2
b1000 8
b111 7
1&
#7880000
b100 =
0,
#7884000
0&
#7902000
b110 7
1&
#7920000
0&
#7938000
10
b100 7
1&
#7956000
0&
#7974000
00
b0 7
1&
#7980000
1,
#7992000
0&
#8010000
b1 7
1&
#8028000
0&
#8046000
1/
b11 7
1&
#8064000
0&
#8080000
b11 =
0,
#8082000
0/
b100 2
b10000 8
b110 7
1&
#8100000
0&
#8118000
10
b100 7
1&
#8136000
0&
#8154000
00
b0 7
1&
#8172000
0&
#8180000
1,
#8190000
b1 7
1&
#8208000
0&
#8226000
1/
b11 7
1&
#8244000
0&
#8262000
0/
b111 7
b101 2
b100000 8
1&
#8280000
0&
b10 =
0,
#8298000
b110 7
1&
#8316000
0&
#8334000
10
b100 7
1&
#8352000
0&
#8370000
00
b0 7
1&
#8380000
1,
#8388000
0&
#8406000
b1 7
1&
#8424000
0&
#8442000
1/
b11 7
1&
#8460000
0&
#8478000
0/
b111 7
b110 2
b1000000 8
1&
#8480000
1+
b1 =
0,
#8496000
0&
#8514000
b1 5
b110 7
1&
#8532000
0&
#8550000
10
b11 5
b100 7
1&
#8568000
0&
#8580000
1,
#8586000
00
b1 7
1&
#8604000
0&
#8622000
1/
b11 7
1&
#8640000
0&
#8658000
0/
b111 2
b10000001 8
b111 7
1&
#8676000
0&
#8680000
0+
b0 =
0,
#8694000
b10 5
b110 7
1&
#8712000
0&
#8730000
10
b0 5
b100 7
1&
#8748000
0&
#8766000
00
b0 7
1&
#8780000
1,
#8784000
0&
#8802000
b1 7
1&
#8820000
0&
#8838000
1/
b11 7
1&
#8856000
0&
#8874000
0/
13
b0 2
b10 8
b111 7
1&
#8880000
b11111111111111111111111111111111 =
0,
#8892000
0&
#8910000
b110 7
03
1"
b100 #
b100 6
1&
#8928000
0&
#8946000
10
0"
b100 7
b11 '
b100 -
b11 .
1&
#8964000
0&
#8980000
b111 =
b11 <
b11 :
#8982000
00
b0 7
1&
#9000000
0&
#9018000
1&
#9036000
0&
#9054000
1&
#9072000
0&
#9080000
1,
#9090000
b1 7
1&
#9108000
0&
#9126000
1/
b11 7
1&
#9144000
0&
#9162000
0/
b1 2
b100 8
b111 7
1&
#9180000
0&
b110 =
0,
#9198000
b110 7
1&
#9216000
0&
#9234000
10
b100 7
1&
#9252000
0&
#9270000
00
b0 7
1&
#9280000
1,
#9288000
0&
#9306000
b1 7
1&
#9324000
0&
#9342000
1/
b11 7
1&
#9360000
0&
#9378000
0/
b10 2
b1000 8
b111 7
1&
#9380000
b101 =
0,
#9396000
0&
#9414000
b110 7
1&
#9432000
0&
#9450000
10
b100 7
1&
#9468000
0&
#9480000
1,
#9486000
00
b1 7
1&
#9504000
0&
#9522000
1/
b11 7
1&
#9540000
0&
#9558000
0/
b111 7
b11 2
b10000 8
1&
#9576000
0&
#9580000
b100 =
0,
#9594000
b110 7
1&
#9612000
0&
#9630000
10
b100 7
1&
#9648000
0&
#9666000
00
b0 7
1&
#9680000
1,
#9684000
0&
#9702000
b1 7
1&
#9720000
0&
#9738000
1/
b11 7
1&
#9756000
0&
#9774000
0/
b111 7
b100 2
b100000 8
1&
#9780000
b11 =
0,
#9792000
0&
#9810000
b110 7
1&
#9828000
0&
#9846000
10
b100 7
1&
#9864000
0&
#9880000
1,
#9882000
00
b1 7
1&
#9900000
0&
#9918000
1/
b11 7
1&
#9936000
0&
#9954000
0/
b101 2
b1000000 8
b111 7
1&
#9972000
0&
#9980000
b10 =
0,
#9990000
b110 7
1&
#10008000
0&
#10026000
10
b100 7
1&
#10044000
0&
#10062000
00
b0 7
1&
#10080000
0&
1,
#10098000
b1 7
1&
#10116000
0&
#10134000
1/
b11 7
1&
#10152000
0&
#10170000
0/
b110 2
b10000000 8
b111 7
1&
#10180000
1+
b1 =
0,
#10188000
0&
#10206000
b1 5
b110 7
1&
#10224000
0&
#10242000
10
b11 5
b100 7
1&
#10260000
0&
#10278000
00
b0 7
1&
#10280000
1,
#10296000
0&
#10314000
b1 7
1&
#10332000
0&
#10350000
1/
b11 7
1&
#10368000
0&
#10380000
b0 =
0,
#10386000
0/
b111 2
b1 8
b110 7
1&
#10404000
0&
#10422000
10
b100 7
1&
#10440000
0&
#10458000
00
b0 7
1&
#10476000
0&
#10480000
1,
#10494000
b1 7
1&
#10512000
0&
#10530000
1/
b11 7
1&
#10548000
0&
#10566000
0/
b111 7
13
b0 2
b11 8
1&
#10580000
b11111111111111111111111111111111 =
0,
#10584000
0&
#10602000
1"
b111 #
b111 6
03
b110 7
1&
#10620000
0&
#10638000
10
b100 7
0"
b100 '
b101 -
b100 .
1&
#10656000
0&
#10674000
00
b0 7
1&
#10680000
0+
b111 =
b100 <
b100 :
#10692000
0&
#10710000
b10 5
1&
#10728000
0&
#10746000
b0 5
1&
#10764000
0&
#10780000
1,
#10782000
b1 7
1&
#10800000
0&
#10818000
1/
b11 7
1&
#10836000
0&
#10854000
0/
b111 7
b1 2
b110 8
1&
#10872000
0&
#10880000
b110 =
0,
#10890000
b110 7
1&
#10908000
0&
#10926000
10
b100 7
1&
#10944000
0&
#10962000
00
b0 7
1&
#10980000
0&
1,
#10998000
b1 7
1&
#11016000
0&
#11034000
1/
b11 7
1&
#11052000
0&
#11070000
0/
b111 7
b10 2
b1100 8
1&
#11080000
b101 =
0,
#11088000
0&
#11106000
b110 7
1&
#11124000
0&
#11142000
10
b100 7
1&
#11160000
0&
#11178000
00
b0 7
1&
#11180000
1,
#11196000
0&
#11214000
b1 7
1&
#11232000
0&
#11250000
1/
b11 7
1&
#11268000
0&
#11280000
b100 =
0,
#11286000
0/
b110 7
b11 2
b11000 8
1&
#11304000
0&
#11322000
10
b100 7
1&
#11340000
0&
#11358000
00
b0 7
1&
#11376000
0&
#11380000
1,
#11394000
b1 7
1&
#11412000
0&
#11430000
1/
b11 7
1&
#11448000
0&
#11466000
0/
b100 2
b110000 8
b111 7
1&
#11480000
b11 =
0,
#11484000
0&
#11502000
b110 7
1&
#11520000
0&
#11538000
10
b100 7
1&
#11556000
0&
#11574000
00
b0 7
1&
#11580000
1,
#11592000
0&
#11610000
b1 7
1&
#11628000
0&
#11646000
1/
b11 7
1&
#11664000
0&
#11680000
1+
b10 =
0,
#11682000
0/
b101 2
b1100000 8
b1 5
b110 7
1&
#11700000
0&
#11718000
10
b11 5
b100 7
1&
#11736000
0&
#11754000
00
b0 7
1&
#11772000
0&
#11780000
1,
#11790000
b1 7
1&
#11808000
0&
#11826000
1/
b11 7
1&
#11844000
0&
#11862000
0/
b111 7
b110 2
b11000001 8
1&
#11880000
0&
0+
b1 =
0,
#11898000
b10 5
b110 7
1&
#11916000
0&
#11934000
10
b0 5
b100 7
1&
#11952000
0&
#11970000
00
b0 7
1&
#11980000
1,
#11988000
0&
#12006000
b1 7
1&
#12024000
0&
#12042000
1/
b11 7
1&
#12060000
0&
#12078000
0/
b111 7
b111 2
b10000010 8
1&
#12080000
b0 =
0,
#12096000
0&
#12114000
b110 7
1&
#12132000
0&
#12150000
10
b100 7
1&
#12168000
0&
#12180000
1,
#12186000
00
b1 7
1&
#12204000
0&
#12222000
1/
b11 7
1&
#12240000
0&
#12258000
0/
13
b0 2
b100 8
b111 7
1&
#12276000
0&
#12280000
b11111111111111111111111111111111 =
0,
#12294000
b110 7
03
1"
b1000 #
b1000 6
1&
#12312000
0&
#12330000
10
0"
b100 7
b101 '
b110 -
b101 .
1&
#12348000
0&
#12366000
00
b0 7
1&
#12380000
b111 =
b101 <
b101 :
#12384000
0&
#12402000
1&
#12420000
0&
#12438000
1&
#12456000
0&
#12474000
1&
#12480000
1,
#12492000
0&
#12510000
b1 7
1&
#12528000
0&
#12546000
1/
b11 7
1&
#12564000
0&
#12580000
b110 =
0,
#12582000
0/
b110 7
b1 2
b1000 8
1&
#12600000
0&
#12618000
10
b100 7
1&
#12636000
0&
#12654000
00
b0 7
1&
#12672000
0&
#12680000
1,
#12690000
b1 7
1&
#12708000
0&
#12726000
1/
b11 7
1&
#12744000
0&
#12762000
0/
b10 2
b10000 8
b111 7
1&
#12780000
0&
b101 =
0,
#12798000
b110 7
1&
#12816000
0&
