fpga/src/rtl/coeff.v
/*
 * coeff.v -- Top-K coefficient extraction FSM
 *
 * Ports flattened for yosys: element [r][c] = flat[(r*8+c)*W +: W]
 * Output arrays flattened: slot k = flat[k*N +: N]
 */

module coeff
    #(parameter W = 16, TOP_K = 5)
    (input wire clk,
     input wire rst,
     input wire bgn,

     input wire signed [W*64-1:0] c_i,

     output reg [3*TOP_K-1:0] r_o,
     output reg [3*TOP_K-1:0] c_o,
     output reg signed [W*TOP_K-1:0] q_o,
     output reg [2:0] n_out,
     output reg done);

        localparam [W-1:0] thresh = 16'd400;
        localparam [3:0] q_shift = 4'd3;
        localparam [3:0] seq_thresh = 4'd6;

        reg [1:0] state;
        localparam IDLE = 2'd0, SCAN = 2'd1, DONE = 2'd2;

        reg [2:0] r_cnt;
        reg [2:0] c_cnt;

        wire skp = (r_cnt + c_cnt > seq_thresh) | (~|{r_cnt, c_cnt});

        wire signed [W-1:0] coeff_val = c_i[(r_cnt*8+c_cnt)*W +: W];
        wire [W-1:0] mag = (coeff_val ^ {W{coeff_val[W-1]}}) + coeff_val[W-1];
        wire [W-1:0] sft = mag - thresh;
        wire [W-1:0] q = sft >>> q_shift;
        wire signed [W-1:0] q_sgn = (q ^ {W{coeff_val[W-1]}}) + coeff_val[W-1];

        wire vld = ~skp & (mag > thresh) & (q != 0);

        wire state_scan = (state == SCAN);
        wire state_idle = (state == IDLE);

        wire wrt_en = state_scan & vld;
        wire clr = state_idle & bgn;

        wire fill = wrt_en & (n_out < TOP_K);
        wire repl = wrt_en & (n_out == TOP_K) & (mag > slot_abs[min_idx]);

        reg [2:0] slot_r [0:TOP_K-1];
        reg [2:0] slot_c [0:TOP_K-1];
        reg signed [W-1:0] slot_q [0:TOP_K-1];
        reg [W-1:0] slot_abs [0:TOP_K-1];
        reg [2:0] min_idx;

        // min rescan: find slot with smallest abs_q
        wire [2:0] m01  = slot_abs[0] < slot_abs[1] ? 0 : 1;
        wire [2:0] m23  = slot_abs[2] < slot_abs[3] ? 2 : 3;
        wire [2:0] m013 = slot_abs[m01] < slot_abs[m23] ? m01 : m23;
        wire [2:0] nmin = slot_abs[m013] < slot_abs[4] ? m013 : 4;

        integer k;

        always @(posedge clk) begin
                done <= (state == DONE);

                if (rst) begin
                        state <= IDLE;
                        n_out <= 3'd0;
                        r_cnt <= 3'd0;
                        c_cnt <= 3'd0;
                end else if (clr) begin
                        state <= SCAN;
                        r_cnt <= 3'd0;
                        c_cnt <= 3'd0;
                        n_out <= 3'd0;
                end else begin
                        c_cnt <= c_cnt + state_scan;
                        r_cnt <= r_cnt + (state_scan & c_cnt == 7);

                        if (state_scan & r_cnt == 7 & c_cnt == 7)
                                state <= DONE;

                        if (state == DONE)
                                state <= IDLE;

                        slot_r[n_out]   <= fill ? r_cnt : slot_r[n_out];
                        slot_c[n_out]   <= fill ? c_cnt : slot_c[n_out];
                        slot_q[n_out]   <= fill ? q_sgn : slot_q[n_out];
                        slot_abs[n_out] <= fill ? mag : slot_abs[n_out];
                        n_out           <= fill ? n_out + 1 : n_out;

                        slot_r[min_idx]   <= repl ? r_cnt : slot_r[min_idx];
                        slot_c[min_idx]   <= repl ? c_cnt : slot_c[min_idx];
                        slot_q[min_idx]   <= repl ? q_sgn : slot_q[min_idx];
                        slot_abs[min_idx] <= repl ? mag : slot_abs[min_idx];

                        min_idx <= (fill | repl) ? nmin : min_idx;
                end

                if (state == DONE) begin
                        for (k = 0; k < TOP_K; k = k + 1) begin
                                r_o[k*3 +: 3] <= slot_r[k];
                                c_o[k*3 +: 3] <= slot_c[k];
                                q_o[k*W +: W] <= slot_q[k];
                        end
                end
        end
endmodule

fpga/sim/coeff_tb.v
`timescale 1ns / 1ps

module coeff_tb;

        localparam W = 16;
        localparam TOP_K = 5;
        localparam CLK = 10;

        reg clk, rst;
        reg bgn;
        reg signed [W*64-1:0] c_i;
        wire [3*TOP_K-1:0] r_o, c_o;
        wire signed [W*TOP_K-1:0] q_o;
        wire [2:0] n_out;
        wire done;

        coeff #(.W(W), .TOP_K(TOP_K)) dut(
            .clk(clk), .rst(rst), .bgn(bgn),
            .c_i(c_i),
            .r_o(r_o), .c_o(c_o), .q_o(q_o),
            .n_out(n_out), .done(done)
        );

        initial begin clk = 0; forever #(CLK/2) clk = ~clk; end

        integer errors;
        integer i;

        task pulse_bgn;
                begin
                        @(posedge clk);
                        bgn <= 1;
                        @(posedge clk);
                        bgn <= 0;
                end
        endtask

        task wait_done;
                begin
                        @(posedge done);
                        @(posedge clk);
                end
        endtask

        initial begin
                $dumpfile("coeff_tb.vcd");
                $dumpvars(0, coeff_tb);
                errors = 0;
                bgn = 0;
                c_i = {(W*64){1'b0}};

                rst = 1;
                #(CLK*5);
                rst = 0;
                #(CLK*2);

                // ------------------------------------------------
                // Test 1: all zeros -- n_out should be 0
                // ------------------------------------------------
                $display("[TEST 1] All zeros");
                pulse_bgn;
                wait_done;
                if (n_out !== 3'd0) begin
                        $display("  FAIL: n_out=%0d, expected 0", n_out);
                        errors = errors + 1;
                end else
                        $display("  PASS: n_out=0");

                // ------------------------------------------------
                // Test 2: single large coefficient at [1][1]
                // (r+c=2 <= 6, so not masked by seq_msk -- but
                //  coeff.v doesn't apply seq_msk, that's external)
                // Set coeff [1][1] = 1000 (above thresh=400)
                // ------------------------------------------------
                $display("[TEST 2] Single coeff at [1][1]=1000");
                c_i = {(W*64){1'b0}};
                c_i[(1*8+1)*W +: W] = 16'sd1000;
                pulse_bgn;
                wait_done;
                $display("  n_out=%0d", n_out);
                if (n_out < 1) begin
                        $display("  FAIL: expected n_out >= 1");
                        errors = errors + 1;
                end else begin
                        $display("  slot0: r=%0d c=%0d q=%0d",
                                 r_o[0*3 +: 3], c_o[0*3 +: 3],
                                 $signed(q_o[0*W +: W]));
                        if (r_o[0*3 +: 3] !== 3'd1 || c_o[0*3 +: 3] !== 3'd1) begin
                                $display("  FAIL: wrong r/c");
                                errors = errors + 1;
                        end else
                                $display("  PASS");
                end

                // ------------------------------------------------
                // Test 3: n_out clears between blocks (Bug 2 regression)
                // Run all-zeros after Test 2 -- n_out must reset to 0
                // ------------------------------------------------
                $display("[TEST 3] n_out clears on new block");
                c_i = {(W*64){1'b0}};
                pulse_bgn;
                wait_done;
                if (n_out !== 3'd0) begin
                        $display("  FAIL: n_out=%0d after zero block (not cleared!)",
                                 n_out);
                        errors = errors + 1;
                end else
                        $display("  PASS: n_out=0 after zero block");

                // ------------------------------------------------
                // Test 4: negative coefficient at [2][3] = -800
                // ------------------------------------------------
                $display("[TEST 4] Negative coeff [2][3]=-800");
                c_i = {(W*64){1'b0}};
                c_i[(2*8+3)*W +: W] = -16'sd800;
                pulse_bgn;
                wait_done;
                if (n_out < 1) begin
                        $display("  FAIL: n_out=%0d", n_out);
                        errors = errors + 1;
                end else begin
                        $display("  slot0: r=%0d c=%0d q=%0d",
                                 r_o[0*3 +: 3], c_o[0*3 +: 3],
                                 $signed(q_o[0*W +: W]));
                        if ($signed(q_o[0*W +: W]) >= 0) begin
                                $display("  FAIL: quantized coeff should be negative");
                                errors = errors + 1;
                        end else
                                $display("  PASS: negative q");
                end

                // ------------------------------------------------
                // Test 5: more than TOP_K coefficients (replacement)
                // Place 7 large coefficients, only 5 should survive
                // ------------------------------------------------
                $display("[TEST 5] TOP_K overflow (7 coeffs, keep best 5)");
                c_i = {(W*64){1'b0}};
                c_i[(0*8+1)*W +: W] = 16'sd500;
                c_i[(0*8+2)*W +: W] = 16'sd600;
                c_i[(0*8+3)*W +: W] = 16'sd700;
                c_i[(1*8+0)*W +: W] = 16'sd800;
                c_i[(1*8+1)*W +: W] = 16'sd900;
                c_i[(1*8+2)*W +: W] = 16'sd1000;
                c_i[(2*8+0)*W +: W] = 16'sd1100;
                pulse_bgn;
                wait_done;
                $display("  n_out=%0d", n_out);
                if (n_out !== 3'd5) begin
                        $display("  FAIL: expected n_out=5");
                        errors = errors + 1;
                end else
                        $display("  PASS: capped at TOP_K");

                for (i = 0; i < TOP_K; i = i + 1)
                        $display("  slot[%0d]: r=%0d c=%0d q=%0d",
                                 i, r_o[i*3+:3], c_o[i*3+:3],
                                 $signed(q_o[i*W+:W]));

                // ------------------------------------------------
                // Test 6: coefficients at high sequency (r+c > 6)
                // coeff.v itself does NOT mask these -- it should find them
                // (seq_msk is applied externally before coeff input)
                // ------------------------------------------------
                $display("[TEST 6] High-sequency coeff at [7][7]=2000");
                c_i = {(W*64){1'b0}};
                c_i[(7*8+7)*W +: W] = 16'sd2000;
                pulse_bgn;
                wait_done;
                // r+c=14 > 6, but skp = (r_cnt+c_cnt > seq_thresh=6) | DC
                // So coeff.v DOES skip this internally!
                $display("  n_out=%0d (should be 0, skipped by internal sequency)",
                         n_out);
                if (n_out !== 3'd0) begin
                        $display("  FAIL");
                        errors = errors + 1;
                end else
                        $display("  PASS");

                #(CLK*10);
                $display("\n===========================================");
                if (errors == 0) $display("*** PASS ***");
                else $display("*** FAIL *** (%0d errors)", errors);
                $display("===========================================");
                $finish;
        end

        initial begin
                #100000;
                $display("ERROR: timeout");
                $finish;
        end
endmodule

fpga/sim/coeff_tb.vcd
$date
	Sat Apr 25 13:54:24 2026
$end
$version
	Icarus Verilog
$end
$timescale
	1ps
$end
$scope module coeff_tb $end
$var wire 15 ! r_o [14:0] $end
$var wire 80 " q_o [79:0] $end
$var wire 3 # n_out [2:0] $end
$var wire 1 $ done $end
$var wire 15 % c_o [14:0] $end
$var parameter 32 & CLK $end
$var parameter 32 ' TOP_K $end
$var parameter 32 ( W $end
$var reg 1 ) bgn $end
$var reg 1024 * c_i [1023:0] $end
$var reg 1 + clk $end
$var reg 1 , rst $end
$var integer 32 - errors [31:0] $end
$var integer 32 . i [31:0] $end
$scope module dut $end
$var wire 1 ) bgn $end
$var wire 1024 / c_i [1023:0] $end
$var wire 1 + clk $end
$var wire 1 0 clr $end
$var wire 1 1 fill $end
$var wire 1 2 repl $end
$var wire 1 , rst $end
$var wire 1 3 skp $end
$var wire 1 4 vld $end
$var wire 1 5 wrt_en $end
$var wire 1 6 state_scan $end
$var wire 1 7 state_idle $end
$var wire 16 8 sft [15:0] $end
$var wire 16 9 q_sgn [15:0] $end
$var wire 16 : q [15:0] $end
$var wire 3 ; nmin [2:0] $end
$var wire 16 < mag [15:0] $end
$var wire 3 = m23 [2:0] $end
$var wire 3 > m013 [2:0] $end
$var wire 3 ? m01 [2:0] $end
$var wire 16 @ coeff_val [15:0] $end
$var parameter 2 A DONE $end
$var parameter 2 B IDLE $end
$var parameter 2 C SCAN $end
$var parameter 32 D TOP_K $end
$var parameter 32 E W $end
$var parameter 4 F q_shift $end
$var parameter 4 G seq_thresh $end
$var parameter 16 H thresh $end
$var reg 3 I c_cnt [2:0] $end
$var reg 15 J c_o [14:0] $end
$var reg 1 $ done $end
$var reg 3 K min_idx [2:0] $end
$var reg 3 L n_out [2:0] $end
$var reg 80 M q_o [79:0] $end
$var reg 3 N r_cnt [2:0] $end
$var reg 15 O r_o [14:0] $end
$var reg 2 P state [1:0] $end
$var integer 32 Q k [31:0] $end
$upscope $end
$scope task pulse_bgn $end
$upscope $end
$scope task wait_done $end
$upscope $end
$upscope $end
$enddefinitions $end
$comment Show the parameter values. $end
$dumpall
b110010000 H
b110 G
b11 F
b10000 E
b101 D
b1 C
b0 B
b10 A
b10000 (
b101 '
b1010 &
$end
#0
$dumpvars
bx Q
bx P
bx O
bx N
bx M
bx L
bx K
bx J
bx I
bx @
b0x ?
b0xx >
b1x =
bx <
bx ;
b0xxxxxxxxxxxxx :
bx 9
bx 8
x7
x6
x5
x4
x3
x2
x1
00
b0 /
bx .
b0 -
1,
0+
b0 *
0)
bx %
x$
bx #
bx "
bx !
$end
#5000
b1111111001110 9
04
b1111111001110 :
b1111111001110000 8
b0 <
02
13
01
05
b0 @
b0 I
b0 N
b0 #
b0 L
06
17
b0 P
1+
#10000
0+
#15000
0$
1+
#20000
0+
#25000
1+
#30000
0+
#35000
1+
#40000
0+
#45000
1+
#50000
0+
0,
#55000
1+
#60000
0+
#65000
1+
#70000
0+
#75000
10
1)
1+
#80000
0+
#85000
00
0)
16
07
b1 P
1+
#90000
0+
#95000
03
b1 I
1+
#100000
0+
#105000
b10 I
1+
#110000
0+
#115000
b11 I
1+
#120000
0+
#125000
b100 I
1+
#130000
0+
#135000
b101 I
1+
#140000
0+
#145000
b110 I
1+
#150000
0+
#155000
13
b111 I
1+
#160000
0+
#165000
03
b1 N
b0 I
1+
#170000
0+
#175000
b1 I
1+
#180000
0+
#185000
b10 I
1+
#190000
0+
#195000
b11 I
1+
#200000
0+
#205000
b100 I
1+
#210000
0+
#215000
b101 I
1+
#220000
0+
#225000
13
b110 I
1+
#230000
0+
#235000
b111 I
1+
#240000
0+
#245000
03
b10 N
b0 I
1+
#250000
0+
#255000
b1 I
1+
#260000
0+
#265000
b10 I
1+
#270000
0+
#275000
b11 I
1+
#280000
0+
#285000
b100 I
1+
#290000
0+
#295000
13
b101 I
1+
#300000
0+
#305000
b110 I
1+
#310000
0+
#315000
b111 I
1+
#320000
0+
#325000
03
b11 N
b0 I
1+
#330000
0+
#335000
b1 I
1+
#340000
0+
#345000
b10 I
1+
#350000
0+
#355000
b11 I
1+
#360000
0+
#365000
13
b100 I
1+
#370000
0+
#375000
b101 I
1+
#380000
0+
#385000
b110 I
1+
#390000
0+
#395000
b111 I
1+
#400000
0+
#405000
03
b100 N
b0 I
1+
#410000
0+
#415000
b1 I
1+
#420000
0+
#425000
b10 I
1+
#430000
0+
#435000
13
b11 I
1+
#440000
0+
#445000
b100 I
1+
#450000
0+
#455000
b101 I
1+
#460000
0+
#465000
b110 I
1+
#470000
0+
#475000
b111 I
1+
#480000
0+
#485000
03
b101 N
b0 I
1+
#490000
0+
#495000
b1 I
1+
#500000
0+
#505000
13
b10 I
1+
#510000
0+
#515000
b11 I
1+
#520000
0+
#525000
b100 I
1+
#530000
0+
#535000
b101 I
1+
#540000
0+
#545000
b110 I
1+
#550000
0+
#555000
b111 I
1+
#560000
0+
#565000
03
b110 N
b0 I
1+
#570000
0+
#575000
13
b1 I
1+
#580000
0+
#585000
b10 I
1+
#590000
0+
#595000
b11 I
1+
#600000
0+
#605000
b100 I
1+
#610000
0+
#615000
b101 I
1+
#620000
0+
#625000
b110 I
1+
#630000
0+
#635000
b111 I
1+
#640000
0+
#645000
b111 N
b0 I
1+
#650000
0+
#655000
b1 I
1+
#660000
0+
#665000
b10 I
1+
#670000
0+
#675000
b11 I
1+
#680000
0+
#685000
b100 I
1+
#690000
0+
#695000
b101 I
1+
#700000
0+
#705000
b110 I
1+
#710000
0+
#715000
b111 I
1+
#720000
0+
#725000
06
b10 P
b0 N
b0 I
1+
#730000
0+
#735000
17
b0 P
1$
b101 Q
1+
#740000
0+
#745000
0$
b1111101000000000000000000000000000000000000000000000000000000000000000000000000000000000000000000000000000000000000000000000000000000000000000000000000000 *
b1111101000000000000000000000000000000000000000000000000000000000000000000000000000000000000000000000000000000000000000000000000000000000000000000000000000 /
1+
#750000
0+
#755000
10
1)
1+
#760000
0+
#765000
00
0)
16
07
b1 P
1+
#770000
0+
#775000
03
b1 I
1+
#780000
0+
#785000
b10 I
1+
#790000
0+
#795000
b11 I
1+
#800000
0+
#805000
b100 I
1+
#810000
0+
#815000
b101 I
1+
#820000
0+
#825000
b110 I
1+
#830000
0+
#835000
13
b111 I
1+
#840000
0+
#845000
03
b1 N
b0 I
1+
#850000
0+
#855000
11
15
b1001011 9
14
b1001011 :
b1001011000 8
b1111101000 <
b1111101000 @
b1 I
1+
#860000
0+
#865000
01
05
b1111111001110 9
04
b1111111001110 :
b1111111001110000 8
b0 <
b1 #
b1 L
b0 @
b10 I
1+
#870000
0+
#875000
b11 I
1+
#880000
0+
#885000
b100 I
1+
#890000
0+
#895000
b101 I
1+
#900000
0+
#905000
13
b110 I
1+
#910000
0+
#915000
b111 I
1+
#920000
0+
#925000
03
b10 N
b0 I
1+
#930000
0+
#935000
b1 I
1+
#940000
0+
#945000
b10 I
1+
#950000
0+
#955000
b11 I
1+
#960000
0+
#965000
b100 I
1+
#970000
0+
#975000
13
b101 I
1+
#980000
0+
#985000
b110 I
1+
#990000
0+
#995000
b111 I
1+
#1000000
0+
#1005000
03
b11 N
b0 I
1+
#1010000
0+
#1015000
b1 I
1+
#1020000
0+
#1025000
b10 I
1+
#1030000
0+
#1035000
b11 I
1+
#1040000
0+
#1045000
13
b100 I
1+
#1050000
0+
#1055000
b101 I
1+
#1060000
0+
#1065000
b110 I
1+
#1070000
0+
#1075000
b111 I
1+
#1080000
0+
#1085000
03
b100 N
b0 I
1+
#1090000
0+
#1095000
b1 I
1+
#1100000
0+
#1105000
b10 I
1+
#1110000
0+
#1115000
13
b11 I
1+
#1120000
0+
#1125000
b100 I
1+
#1130000
0+
#1135000
b101 I
1+
#1140000
0+
#1145000
b110 I
1+
#1150000
0+
#1155000
b111 I
1+
#1160000
0+
#1165000
03
b101 N
b0 I
1+
#1170000
0+
#1175000
b1 I
1+
#1180000
0+
#1185000
13
b10 I
1+
#1190000
0+
#1195000
b11 I
1+
#1200000
0+
#1205000
b100 I
1+
#1210000
0+
#1215000
b101 I
1+
#1220000
0+
#1225000
b110 I
1+
#1230000
0+
#1235000
b111 I
1+
#1240000
0+
#1245000
03
b110 N
b0 I
1+
#1250000
0+
#1255000
13
b1 I
1+
#1260000
0+
#1265000
b10 I
1+
#1270000
0+
#1275000
b11 I
1+
#1280000
0+
#1285000
b100 I
1+
#1290000
0+
#1295000
b101 I
1+
#1300000
0+
#1305000
b110 I
1+
#1310000
0+
#1315000
b111 I
1+
#1320000
0+
#1325000
b111 N
b0 I
1+
#1330000
0+
#1335000
b1 I
1+
#1340000
0+
#1345000
b10 I
1+
#1350000
0+
#1355000
b11 I
1+
#1360000
0+
#1365000
b100 I
1+
#1370000
0+
#1375000
b101 I
1+
#1380000
0+
#1385000
b110 I
1+
#1390000
0+
#1395000
b111 I
1+
#1400000
0+
#1405000
06
b10 P
b0 N
b0 I
1+
#1410000
0+
#1415000
bx0000000001001011 "
bx0000000001001011 M
bx001 %
bx001 J
bx001 !
bx001 O
17
b0 P
1$
b101 Q
1+
#1420000
0+
#1425000
0$
b0 *
b0 /
1+
#1430000
0+
#1435000
10
1)
1+
#1440000
0+
#1445000
00
0)
b0 #
b0 L
16
07
b1 P
1+
#1450000
0+
#1455000
03
b1 I
1+
#1460000
0+
#1465000
b10 I
1+
#1470000
0+
#1475000
b11 I
1+
#1480000
0+
#1485000
b100 I
1+
#1490000
0+
#1495000
b101 I
1+
#1500000
0+
#1505000
b110 I
1+
#1510000
0+
#1515000
13
b111 I
1+
#1520000
0+
#1525000
03
b1 N
b0 I
1+
#1530000
0+
#1535000
b1 I
1+
#1540000
0+
#1545000
b10 I
1+
#1550000
0+
#1555000
b11 I
1+
#1560000
0+
#1565000
b100 I
1+
#1570000
0+
#1575000
b101 I
1+
#1580000
0+
#1585000
13
b110 I
1+
#1590000
0+
#1595000
b111 I
1+
#1600000
0+
#1605000
03
b10 N
b0 I
1+
#1610000
0+
#1615000
b1 I
1+
#1620000
0+
#1625000
b10 I
1+
#1630000
0+
#1635000
b11 I
1+
#1640000
0+
#1645000
b100 I
1+
#1650000
0+
#1655000
13
b101 I
1+
#1660000
0+
#1665000
b110 I
1+
#1670000
0+
#1675000
b111 I
1+
#1680000
0+
#1685000
03
b11 N
b0 I
1+
#1690000
0+
#1695000
b1 I
1+
#1700000
0+
#1705000
b10 I
1+
#1710000
0+
#1715000
b11 I
1+
#1720000
0+
#1725000
13
b100 I
1+
#1730000
0+
#1735000
b101 I
1+
#1740000
0+
#1745000
b110 I
1+
#1750000
0+
#1755000
b111 I
1+
#1760000
0+
#1765000
03
b100 N
b0 I
1+
#1770000
0+
#1775000
b1 I
1+
#1780000
0+
#1785000
b10 I
1+
#1790000
0+
#1795000
13
b11 I
1+
#1800000
0+
#1805000
b100 I
1+
#1810000
0+
#1815000
b101 I
1+
#1820000
0+
#1825000
b110 I
1+
#1830000
0+
#1835000
b111 I
1+
#1840000
0+
#1845000
03
b101 N
b0 I
1+
#1850000
0+
#1855000
b1 I
1+
#1860000
0+
#1865000
13
b10 I
1+
#1870000
0+
#1875000
b11 I
1+
#1880000
0+
#1885000
b100 I
1+
#1890000
0+
#1895000
b101 I
1+
#1900000
0+
#1905000
b110 I
1+
#1910000
0+
#1915000
b111 I
1+
#1920000
0+
#1925000
03
b110 N
b0 I
1+
#1930000
0+
#1935000
13
b1 I
1+
#1940000
0+
#1945000
b10 I
1+
#1950000
0+
#1955000
b11 I
1+
#1960000
0+
#1965000
b100 I
1+
#1970000
0+
#1975000
b101 I
1+
#1980000
0+
#1985000
b110 I
1+
#1990000
0+
#1995000
b111 I
1+
#2000000
0+
#2005000
b111 N
b0 I
1+
#2010000
0+
#2015000
b1 I
1+
#2020000
0+
#2025000
b10 I
1+
#2030000
0+
#2035000
b11 I
1+
#2040000
0+
#2045000
b100 I
1+
#2050000
0+
#2055000
b101 I
1+
#2060000
0+
#2065000
b110 I
1+
#2070000
0+
#2075000
b111 I
1+
#2080000
0+
#2085000
06
b10 P
b0 N
b0 I
1+
#2090000
0+
#2095000
17
b0 P
1$
b101 Q
1+
#2100000
0+
#2105000
0$
b11111100111000000000000000000000000000000000000000000000000000000000000000000000000000000000000000000000000000000000000000000000000000000000000000000000000000000000000000000000000000000000000000000000000000000000000000000000000000000000000000000000000000000000000000000000000000000000000000000000000000000000000000000000 *
b11111100111000000000000000000000000000000000000000000000000000000000000000000000000000000000000000000000000000000000000000000000000000000000000000000000000000000000000000000000000000000000000000000000000000000000000000000000000000000000000000000000000000000000000000000000000000000000000000000000000000000000000000000000 /
1+
#2110000
0+
#2115000
10
1)
1+
#2120000
0+
#2125000
00
0)
16
07
b1 P
1+
#2130000
0+
#2135000
03
b1 I
1+
#2140000
0+
#2145000
b10 I
1+
#2150000
0+
#2155000
b11 I
1+
#2160000
0+
#2165000
b100 I
1+
#2170000
0+
#2175000
b101 I
1+
#2180000
0+
#2185000
b110 I
1+
#2190000
0+
#2195000
13
b111 I
1+
#2200000
0+
#2205000
03
b1 N
b0 I
1+
#2210000
0+
#2215000
b1 I
1+
#2220000
0+
#2225000
b10 I
1+
#2230000
0+
#2235000
b11 I
1+
#2240000
0+
#2245000
b100 I
1+
#2250000
0+
#2255000
b101 I
1+
#2260000
0+
#2265000
13
b110 I
1+
#2270000
0+
#2275000
b111 I
1+
#2280000
0+
#2285000
03
b10 N
b0 I
1+
#2290000
0+
#2295000
b1 I
1+
#2300000
0+
#2305000
b10 I
1+
#2310000
0+
#2315000
11
15
14
b110010 :
b1111111111001110 9
b110010000 8
b1100100000 <
b1111110011100000 @
b11 I
1+
#2320000
0+
#2325000
01
05
04
b1111111001110 :
b1111111001110 9
b1111111001110000 8
b0 <
b1 #
b1 L
b0 @
b100 I
1+
#2330000
0+
#2335000
13
b101 I
1+
#2340000
0+
#2345000
b110 I
1+
#2350000
0+
#2355000
b111 I
1+
#2360000
0+
#2365000
03
b11 N
b0 I
1+
#2370000
0+
#2375000
b1 I
1+
#2380000
0+
#2385000
b10 I
1+
#2390000
0+
#2395000
b11 I
1+
#2400000
0+
#2405000
13
b100 I
1+
#2410000
0+
#2415000
b101 I
1+
#2420000
0+
#2425000
b110 I
1+
#2430000
0+
#2435000
b111 I
1+
#2440000
0+
#2445000
03
b100 N
b0 I
1+
#2450000
0+
#2455000
b1 I
1+
#2460000
0+
#2465000
b10 I
1+
#2470000
0+
#2475000
13
b11 I
1+
#2480000
0+
#2485000
b100 I
1+
#2490000
0+
#2495000
b101 I
1+
#2500000
0+
#2505000
b110 I
1+
#2510000
0+
#2515000
b111 I
1+
#2520000
0+
#2525000
03
b101 N
b0 I
1+
#2530000
0+
#2535000
b1 I
1+
#2540000
0+
#2545000
13
b10 I
1+
#2550000
0+
#2555000
b11 I
1+
#2560000
0+
#2565000
b100 I
1+
#2570000
0+
#2575000
b101 I
1+
#2580000
0+
#2585000
b110 I
1+
#2590000
0+
#2595000
b111 I
1+
#2600000
0+
#2605000
03
b110 N
b0 I
1+
#2610000
0+
#2615000
13
b1 I
1+
#2620000
0+
#2625000
b10 I
1+
#2630000
0+
#2635000
b11 I
1+
#2640000
0+
#2645000
b100 I
1+
#2650000
0+
#2655000
b101 I
1+
#2660000
0+
#2665000
b110 I
1+
#2670000
0+
#2675000
b111 I
1+
#2680000
0+
#2685000
b111 N
b0 I
1+
#2690000
0+
#2695000
b1 I
1+
#2700000
0+
#2705000
b10 I
1+
#2710000
0+
#2715000
b11 I
1+
#2720000
0+
#2725000
b100 I
1+
#2730000
0+
#2735000
b101 I
1+
#2740000
0+
#2745000
b110 I
1+
#2750000
0+
#2755000
b111 I
1+
#2760000
0+
#2765000
06
b10 P
b0 N
b0 I
1+
#2770000
0+
#2775000
bx1111111111001110 "
bx1111111111001110 M
bx011 %
bx011 J
bx010 !
bx010 O
17
b0 P
1$
b101 Q
1+
#2780000
0+
#2785000
0$
b100010011000000000000000000000000000000000000000000000000000000000000000000000000000000000000000011111010000000001110000100000000110010000000000000000000000000000000000000000000000000000000000000000000000000001010111100000000100101100000000001111101000000000000000000 *
b100010011000000000000000000000000000000000000000000000000000000000000000000000000000000000000000011111010000000001110000100000000110010000000000000000000000000000000000000000000000000000000000000000000000000001010111100000000100101100000000001111101000000000000000000 /
1+
#2790000
0+
#2795000
10
1)
1+
#2800000
0+
#2805000
00
0)
b0 #
b0 L
16
07
b1 P
1+
#2810000
0+
#2815000
11
15
14
b1100 9
b1100 :
03
b1100100 8
b111110100 <
b111110100 @
b1 I
1+
#2820000
0+
#2825000
b11001 9
b11001 :
b11001000 8
b1001011000 <
b1 #
b1 L
b1001011000 @
b10 I
1+
#2830000
0+
#2835000
b100101 9
b100101 :
b0 ?
b100101100 8
b1010111100 <
b10 #
b10 L
b1010111100 @
b11 I
1+
#2840000
0+
#2845000
01
05
b1111111001110 9
04
b1111111001110 :
b1111111001110000 8
b0 <
b11 #
b11 L
b0 @
b100 I
1+
#2850000
0+
#2855000
b101 I
1+
#2860000
0+
#2865000
b110 I
1+
#2870000
0+
#2875000
13
b111 I
1+
#2880000
0+
#2885000
11
15
b110010 9
14
b110010 :
b110010000 8
b1100100000 <
03
b1100100000 @
b1 N
b0 I
1+
#2890000
0+
#2895000
bx00 ;
b111110 9
b0 >
b111110 :
b10 =
b111110100 8
b1110000100 <
b100 #
b100 L
b1110000100 @
b1 I
1+
#2900000
0+
#2905000
b1001011 9
x2
b0 ;
b1001011 :
01
b1001011000 8
b1111101000 <
bx00 K
b101 #
b101 L
b1111101000 @
b10 I
1+
#2910000
0+
#2915000
02
05
b1111111001110 9
04
b1111111001110 :
b1111111001110000 8
b0 <
b0 @
b11 I
1+
#2920000
0+
#2925000
b100 I
1+
#2930000
0+
#2935000
b101 I
1+
#2940000
0+
#2945000
13
b110 I
1+
#2950000
0+
#2955000
b111 I
1+
#2960000
0+
#2965000
x2
15
14
b1010111 9
b1010111 :
03
b1010111100 8
b10001001100 <
b10 N
b10001001100 @
b0 I
1+
#2970000
0+
#2975000
02
05
b1111111001110 9
04
b1111111001110 :
b1111111001110000 8
b0 <
b0 @
b1 I
1+
#2980000
0+
#2985000
b10 I
1+
#2990000
0+
#2995000
b11 I
1+
#3000000
0+
#3005000
b100 I
1+
#3010000
0+
#3015000
13
b101 I
1+
#3020000
0+
#3025000
b110 I
1+
#3030000
0+
#3035000
b111 I
1+
#3040000
0+
#3045000
03
b11 N
b0 @
b0 I
1+
#3050000
0+
#3055000
b1 I
1+
#3060000
0+
#3065000
b10 I
1+
#3070000
0+
#3075000
b11 I
1+
#3080000
0+
#3085000
13
b100 I
1+
#3090000
0+
#3095000
b101 I
1+
#3100000
0+
#3105000
b110 I
1+
#3110000
0+
#3115000
b111 I
1+
#3120000
0+
#3125000
03
b100 N
b0 I
1+
#3130000
0+
#3135000
b1 I
1+
#3140000
0+
#3145000
b10 I
1+
#3150000
0+
#3155000
13
b11 I
1+
#3160000
0+
#3165000
b100 I
1+
#3170000
0+
#3175000
b101 I
1+
#3180000
0+
#3185000
b110 I
1+
#3190000
0+
#3195000
b111 I
1+
#3200000
0+
#3205000
03
b101 N
b0 I
1+
#3210000
0+
#3215000
b1 I
1+
#3220000
0+
#3225000
13
b10 I
1+
#3230000
0+
#3235000
b11 I
1+
#3240000
0+
#3245000
b100 I
1+
#3250000
0+
#3255000
b101 I
1+
#3260000
0+
#3265000
b110 I
1+
#3270000
0+
#3275000
b111 I
1+
#3280000
0+
#3285000
03
b110 N
b0 I
1+
#3290000
0+
#3295000
13
b1 I
1+
#3300000
0+
#3305000
b10 I
1+
#3310000
0+
#3315000
b11 I
1+
#3320000
0+
#3325000
b100 I
1+
#3330000
0+
#3335000
b101 I
1+
#3340000
0+
#3345000
b110 I
1+
#3350000
0+
#3355000
b111 I
1+
#3360000
0+
#3365000
b111 N
b0 I
1+
#3370000
0+
#3375000
b1 I
1+
#3380000
0+
#3385000
b10 I
1+
#3390000
0+
#3395000
b11 I
1+
#3400000
0+
#3405000
b100 I
1+
#3410000
0+
#3415000
b101 I
1+
#3420000
0+
#3425000
b110 I
1+
#3430000
0+
#3435000
b111 I
1+
#3440000
0+
#3445000
06
b10 P
b0 N
b0 I
1+
#3450000
0+
#3455000
b1111100000000000110010000000000010010100000000000110010000000000001100 "
b1111100000000000110010000000000010010100000000000110010000000000001100 M
b1000011010001 %
b1000011010001 J
b1001000000000 !
b1001000000000 O
17
b0 P
1$
b101 Q
1+
#3460000
0+
