fpga/src/rtl/esp_interface.v
//
// esp_interface.v
//
// SPI slave — Mode 0 (CPOL=0 CPHA=0): sample rising, shift falling
// Branchless datapath: AND-mask / OR-combine, if only for async reset
//

module esp_interface
    (input wire clk,
     input wire rst_n,

     input wire esp_mosi,
     output reg esp_miso,
     input wire esp_sclk,
     input wire esp_cs_n,

     output reg [7 : 0] rx_data,
     output reg rx_valid,
     input wire rx_ready,

     input wire [7 : 0] tx_data,
     output wire tx_next,

     output wire cs_active_sync // synchronized CS active level for top.v
    );

        // ==========================================================
        // Synchronizers — 3-stage sclk/cs, 2-stage mosi
        // Pure shift, no branches
        // ==========================================================
        reg [2 : 0] sclk_sync, cs_sync;
        reg [1 : 0] mosi_sync;

        always @(posedge clk or negedge rst_n) begin
                if (!rst_n) begin
                        sclk_sync <= 3'b000;
                        cs_sync <= 3'b111;
                        mosi_sync <= 2'b00;
                end else begin
                        sclk_sync <= {sclk_sync[1 : 0], esp_sclk};
                        cs_sync <= {cs_sync[1 : 0], esp_cs_n};
                        mosi_sync <= {mosi_sync[0], esp_mosi};
                end
        end

        // edge / level detection — combinational
        wire sclk_rise = (sclk_sync[2 : 1] == 2'b01);
        wire sclk_fall = (sclk_sync[2 : 1] == 2'b10);
        wire cs_active = ~cs_sync[2];

        assign cs_active_sync = cs_active;

        // ==========================================================
        // Shift register + bit counter
        //
        // On sclk_rise & cs_active: shift in mosi, increment count
        // On ~cs_active: hold zeros (AND-mask clears)
        // byte_complete when bit_count == 7 on a rising edge
        //
        // shift_next: shift in new bit, AND-masked by (sclk_rise & cs_active)
        //             held at 0 when ~cs_active
        // count_next: (count + 1) on shift, AND-masked to wrap at 8,
        //             zeroed when ~cs_active
        // ==========================================================
        reg [7 : 0] shift_reg;
        reg [2 : 0] bit_count;
        reg byte_ready;

        wire shifting = sclk_rise & cs_active;
        wire byte_done = shifting & (bit_count == 3'd7);
        wire [7 : 0] shifted_in = {shift_reg[6 : 0], mosi_sync[1]};

        // AND-mask: shifting selects new shifted value, ~shifting holds
        // current ~cs_active zeros everything (overrides shifting since
        // shifting requires cs_active)
        wire [7 : 0] shift_next = (shifted_in & {8{shifting}}) |
                                  (shift_reg & {8{~shifting & cs_active}});
        wire [2 : 0] count_inc = (bit_count + 3'd1) &
                                 {3{~byte_done}}; // wraps to 0 on byte_done
        wire [2 : 0] count_next = (count_inc & {3{shifting}}) |
                                  (bit_count & {3{~shifting}});
        wire [2 : 0] count_out = count_next &
                                 {3{cs_active}}; // zero when CS deasserted

        always @(posedge clk or negedge rst_n) begin
                if (!rst_n) begin
                        shift_reg <= 8'h00;
                        bit_count <= 3'd0;
                        byte_ready <= 1'b0;
                end else begin
                        shift_reg <= shift_next & {8{cs_active}};
                        bit_count <= count_out;
                        byte_ready <= byte_done;
                end
        end

        // ==========================================================
        // Output latch — rx_data holds on byte_ready, rx_valid strobes
        //
        // data: AND-mask selects new capture vs hold
        // valid: just byte_ready delayed one cycle (already is — byte_ready
        //        is registered, so rx_valid = byte_ready is the strobe)
        // ==========================================================
        wire [7 : 0] captured = {shift_reg[6 : 0],
                                 mosi_sync[1]}; // include last bit
        wire [7 : 0] data_next = (captured & {8{byte_ready}}) |
                                 (rx_data & {8{~byte_ready}});

        always @(posedge clk or negedge rst_n) begin
                if (!rst_n) begin
                        rx_data <= 8'h00;
                        rx_valid <= 1'b0;
                end else begin
                        rx_data <= data_next;
                        rx_valid <= byte_ready;
                end
        end

        // ==========================================================
        // MISO TX — shift out tx_data, MSB first on falling SCLK
        //
        // tx_next pulses on byte_done so top.v advances to next byte
        // Preload from tx_data on CS assert and each byte boundary
        // ==========================================================
        reg [7 : 0] tx_sr;
        reg byte_done_d, byte_done_dd;

        always @(posedge clk or negedge rst_n)
                if (!rst_n) begin byte_done_d <= 1'b0; byte_done_dd <= 1'b0; end
                else        begin byte_done_d <= byte_done; byte_done_dd <= byte_done_d; end

        assign tx_next = byte_done;

        wire tx_reload = byte_done_dd | (~cs_active);

        always @(posedge clk or negedge rst_n) begin
                if (!rst_n) begin
                        tx_sr <= 8'd0;
                        esp_miso <= 1'b0;
                end else begin
                        if (tx_reload)
                                tx_sr <= tx_data;
                        else if (sclk_fall & cs_active & (bit_count != 3'd0))
                                tx_sr <= {tx_sr[6 : 0], 1'b0};

                        esp_miso <= cs_active ? tx_sr[7] : 1'b0;
                end
        end
endmodule

fpga/sim/esp_interface_tx_tb.v
`timescale 1ns / 1ps

// esp_interface TX path testbench -- accurate top.v tx_buf model.
//
// Models the synchronous BRAM read lag in top.v:
//   tx_rd_ptr advances on tx_next (registered).
//   tx_rd_data = tx_buf[tx_rd_ptr] is a registered read -- reads the OLD ptr.
//   tx_sr is loaded from tx_rd_data on byte_done_d (one cycle after tx_next).
//   Because both happen at the same posedge, tx_sr sees the pre-advance byte.
//
// Bug 1 (MISO shift): byte[N>=1] arrives as correct_byte << 1.
// Bug 3 (BRAM lag):   byte[N>=1] arrives as tx_mem[N-1] (one behind).
// Both must be fixed for all tests to pass.

module esp_interface_tx_tb;

        localparam CLK_PERIOD = 37;
        localparam SPI_HALF = CLK_PERIOD * 6;

        reg clk, rst_n;
        reg tb_mosi, tb_sclk, tb_cs_n;
        wire tb_miso;

        wire [7:0] rx_data;
        wire rx_valid;
        reg rx_ready;

        wire [7:0] tx_data;
        wire tx_next;
        wire cs_active_sync;

        esp_interface dut(
            .clk(clk), .rst_n(rst_n),
            .esp_mosi(tb_mosi), .esp_miso(tb_miso),
            .esp_sclk(tb_sclk), .esp_cs_n(tb_cs_n),
            .rx_data(rx_data), .rx_valid(rx_valid), .rx_ready(rx_ready),
            .tx_data(tx_data), .tx_next(tx_next),
            .cs_active_sync(cs_active_sync)
        );

        initial begin clk = 0; forever #(CLK_PERIOD/2) clk = ~clk; end

        integer errors;

        reg [7:0] tx_mem [0:15];

        initial begin
                tx_mem[0]  = 8'hDE;
                tx_mem[1]  = 8'hAD;
                tx_mem[2]  = 8'hBE;
                tx_mem[3]  = 8'hEF;
                tx_mem[4]  = 8'h01;
                tx_mem[5]  = 8'h23;
                tx_mem[6]  = 8'h45;
                tx_mem[7]  = 8'h67;
                tx_mem[8]  = 8'h89;
                tx_mem[9]  = 8'hAB;
                tx_mem[10] = 8'hCD;
                tx_mem[11] = 8'hEF;
                tx_mem[12] = 8'hFE;
                tx_mem[13] = 8'hDC;
                tx_mem[14] = 8'hBA;
                tx_mem[15] = 8'h98;
        end

        // Accurate top.v tx_buf model.
        // tx_rd_ptr advances on tx_next; resets when CS asserts.
        // tx_rd_data is a registered read of tx_mem[tx_rd_ptr] -- reads the OLD ptr
        // because both the ptr advance and the BRAM address are non-blocking.
        // This means tx_sr is loaded with the PREVIOUS byte on each byte boundary.
        reg [7:0] tx_rd_ptr;
        reg [7:0] tx_rd_data;
        reg       tb_cs_n_d;

        wire cs_assert = tb_cs_n_d & ~tb_cs_n;

        always @(posedge clk or negedge rst_n) begin
                if (!rst_n) begin
                        tx_rd_ptr  <= 8'd0;
                        tx_rd_data <= tx_mem[0];
                        tb_cs_n_d  <= 1'b1;
                end else begin
                        tb_cs_n_d  <= tb_cs_n;
                        if (cs_assert)
                                tx_rd_ptr <= 8'd0;
                        else if (tx_next)
                                tx_rd_ptr <= tx_rd_ptr + 8'd1;
                        tx_rd_data <= tx_mem[tx_rd_ptr]; // reads OLD ptr -- BRAM lag
                end
        end

        assign tx_data = tx_rd_data;

        task spi_xfer_byte;
                output [7:0] captured;
                integer i;
                begin
                        captured = 8'd0;
                        for (i = 7; i >= 0; i = i - 1) begin
                                tb_mosi = 0;
                                #(SPI_HALF);
                                tb_sclk = 1;
                                captured[i] = tb_miso;
                                #(SPI_HALF);
                                tb_sclk = 0;
                        end
                end
        endtask

        reg [7:0] got;
        integer byte_num;

        initial begin
                $dumpfile("esp_interface_tx_tb.vcd");
                $dumpvars(0, esp_interface_tx_tb);
                errors = 0;

                rst_n = 0;
                tb_mosi = 0;
                tb_sclk = 0;
                tb_cs_n = 1;
                rx_ready = 1;

                #(CLK_PERIOD*10);
                rst_n = 1;
                #(CLK_PERIOD*10);

                $display("===========================================");
                $display("ESP Interface TX Path Testbench (accurate)");
                $display("===========================================");

                // ----------------------------------------------------------
                // Test 1: 8-byte sequential readback
                // ----------------------------------------------------------
                $display("\n[TEST 1] 8-byte TX readback");
                tb_cs_n = 0;
                #(CLK_PERIOD * 8);

                for (byte_num = 0; byte_num < 8; byte_num = byte_num + 1) begin
                        spi_xfer_byte(got);
                        $display("  byte[%0d]: got=0x%02X exp=0x%02X %s",
                                 byte_num, got, tx_mem[byte_num],
                                 (got == tx_mem[byte_num]) ? "OK" : "MISMATCH");
                        if (got !== tx_mem[byte_num])
                                errors = errors + 1;
                end

                #(SPI_HALF * 2);
                tb_cs_n = 1;
                #(CLK_PERIOD*20);

                // ----------------------------------------------------------
                // Test 2: CS deassert/reassert -- ptr resets, byte[0] again
                // ----------------------------------------------------------
                $display("\n[TEST 2] CS toggle re-preload");
                tb_cs_n = 0;
                #(CLK_PERIOD * 8);
                spi_xfer_byte(got);
                $display("  first byte after re-CS: got=0x%02X exp=0x%02X %s",
                         got, tx_mem[0],
                         (got == tx_mem[0]) ? "OK" : "MISMATCH");
                if (got !== tx_mem[0])
                        errors = errors + 1;
                #(SPI_HALF * 2);
                tb_cs_n = 1;
                #(CLK_PERIOD*20);

                // ----------------------------------------------------------
                // Test 3: 16 back-to-back bytes, no inter-byte gap
                // ----------------------------------------------------------
                $display("\n[TEST 3] Back-to-back bytes (16 bytes, no gap)");
                rst_n = 0;
                #(CLK_PERIOD*5);
                rst_n = 1;
                #(CLK_PERIOD*10);

                tb_cs_n = 0;
                #(CLK_PERIOD * 8);

                for (byte_num = 0; byte_num < 16; byte_num = byte_num + 1) begin
                        spi_xfer_byte(got);
                        $display("  byte[%0d]: got=0x%02X exp=0x%02X %s",
                                 byte_num, got, tx_mem[byte_num],
                                 (got == tx_mem[byte_num]) ? "OK" : "MISMATCH");
                        if (got !== tx_mem[byte_num])
                                errors = errors + 1;
                end

                #(SPI_HALF * 2);
                tb_cs_n = 1;
                #(CLK_PERIOD*50);

                $display("\n===========================================");
                $display("  Errors: %0d", errors);
                if (errors == 0) $display("*** PASS ***");
                else $display("*** FAIL ***");
                $display("===========================================");
                $finish;
        end

        initial begin
                #5000000;
                $display("ERROR: timeout");
                $finish;
        end
endmodule

fpga/sim/esp_interface_tx_tb.vcd
$date
	Sat Apr 25 13:54:24 2026
$end
$version
	Icarus Verilog
$end
$timescale
	1ps
$end
$scope module esp_interface_tx_tb $end
$var wire 1 ! cs_assert $end
$var wire 8 " tx_data [7:0] $end
$var wire 1 # tx_next $end
$var wire 1 $ tb_miso $end
$var wire 1 % rx_valid $end
$var wire 8 & rx_data [7:0] $end
$var wire 1 ' cs_active_sync $end
$var parameter 32 ( CLK_PERIOD $end
$var parameter 64 ) SPI_HALF $end
$var reg 1 * clk $end
$var reg 8 + got [7:0] $end
$var reg 1 , rst_n $end
$var reg 1 - rx_ready $end
$var reg 1 . tb_cs_n $end
$var reg 1 / tb_cs_n_d $end
$var reg 1 0 tb_mosi $end
$var reg 1 1 tb_sclk $end
$var reg 8 2 tx_rd_data [7:0] $end
$var reg 8 3 tx_rd_ptr [7:0] $end
$var integer 32 4 byte_num [31:0] $end
$var integer 32 5 errors [31:0] $end
$scope module dut $end
$var wire 1 6 byte_done $end
$var wire 1 * clk $end
$var wire 3 7 count_inc [2:0] $end
$var wire 3 8 count_next [2:0] $end
$var wire 3 9 count_out [2:0] $end
$var wire 1 : cs_active $end
$var wire 1 ' cs_active_sync $end
$var wire 8 ; data_next [7:0] $end
$var wire 1 . esp_cs_n $end
$var wire 1 0 esp_mosi $end
$var wire 1 1 esp_sclk $end
$var wire 1 , rst_n $end
$var wire 1 - rx_ready $end
$var wire 8 < shift_next [7:0] $end
$var wire 1 = shifting $end
$var wire 8 > tx_data [7:0] $end
$var wire 1 # tx_next $end
$var wire 1 ? tx_reload $end
$var wire 8 @ shifted_in [7:0] $end
$var wire 1 A sclk_rise $end
$var wire 1 B sclk_fall $end
$var wire 8 C captured [7:0] $end
$var reg 3 D bit_count [2:0] $end
$var reg 1 E byte_done_d $end
$var reg 1 F byte_done_dd $end
$var reg 1 G byte_ready $end
$var reg 3 H cs_sync [2:0] $end
$var reg 1 $ esp_miso $end
$var reg 2 I mosi_sync [1:0] $end
$var reg 8 J rx_data [7:0] $end
$var reg 1 % rx_valid $end
$var reg 3 K sclk_sync [2:0] $end
$var reg 8 L shift_reg [7:0] $end
$var reg 8 M tx_sr [7:0] $end
$upscope $end
$scope task spi_xfer_byte $end
$var reg 8 N captured [7:0] $end
$var integer 32 O i [31:0] $end
$upscope $end
$upscope $end
$enddefinitions $end
$comment Show the parameter values. $end
$dumpall
b11011110 )
b100101 (
$end
#0
$dumpvars
bx O
bx N
b0 M
b0 L
b0 K
b0 J
b0 I
b111 H
0G
0F
0E
b0 D
b0 C
0B
0A
b0 @
1?
b11011110 >
0=
b0 <
b0 ;
0:
b0 9
b0 8
b1 7
06
b0 5
bx 4
b0 3
b11011110 2
01
00
1/
1.
1-
0,
bx +
0*
0'
b0 &
0%
0$
0#
b11011110 "
0!
$end
#18000
1*
#36000
0*
#54000
1*
#72000
0*
#90000
1*
#108000
0*
#126000
1*
#144000
0*
#162000
1*
#180000
0*
#198000
1*
#216000
0*
#234000
1*
#252000
0*
#270000
1*
#288000
0*
#306000
1*
#324000
0*
#342000
1*
#360000
0*
#370000
1,
#378000
b11011110 M
1*
#396000
0*
#414000
1*
#432000
0*
#450000
1*
#468000
0*
#486000
1*
#504000
0*
#522000
1*
#540000
0*
#558000
1*
#576000
0*
#594000
1*
#612000
0*
#630000
1*
#648000
0*
#666000
1*
#684000
0*
#702000
1*
#720000
0*
#738000
1*
#740000
1!
0.
#756000
0*
#774000
0!
b110 H
0/
1*
#792000
0*
#810000
b100 H
1*
#828000
0*
#846000
0?
1'
1:
b0 H
1*
#864000
0*
#882000
1$
1*
#900000
0*
#918000
1*
#936000
0*
#954000
1*
#972000
0*
#990000
1*
#1008000
0*
#1026000
1*
#1036000
b111 O
b0 N
b0 4
#1044000
0*
#1062000
1*
#1080000
0*
#1098000
1*
#1116000
0*
#1134000
1*
#1152000
0*
#1170000
1*
#1188000
0*
#1206000
1*
#1224000
0*
#1242000
1*
#1258000
b10000000 N
11
#1260000
0*
#1278000
b1 K
1*
#1296000
0*
#1314000
b1 9
b1 8
1=
1A
b11 K
1*
#1332000
0*
#1350000
b1 9
b1 8
0=
0A
b10 7
b111 K
b1 D
1*
#1368000
0*
#1386000
1*
#1404000
0*
#1422000
1*
#1440000
0*
#1458000
1*
#1476000
0*
#1480000
b110 O
01
#1494000
b110 K
1*
#1512000
0*
#1530000
1B
b100 K
1*
#1548000
0*
#1566000
0B
b0 K
b10111100 M
1*
#1584000
0*
#1602000
1*
#1620000
0*
#1638000
1*
#1656000
0*
#1674000
1*
#1692000
0*
#1702000
b11000000 N
11
#1710000
b1 K
1*
#1728000
0*
#1746000
b10 9
b10 8
1=
1A
b11 K
1*
#1764000
0*
#1782000
b10 9
b10 8
0=
0A
b11 7
b111 K
b10 D
1*
#1800000
0*
#1818000
1*
#1836000
0*
#1854000
1*
#1872000
0*
#1890000
1*
#1908000
0*
#1924000
b101 O
01
#1926000
b110 K
1*
#1944000
0*
#1962000
1B
b100 K
1*
#1980000
0*
#1998000
0B
b0 K
b1111000 M
1*
#2016000
0*
#2034000
0$
1*
#2052000
0*
#2070000
1*
#2088000
0*
#2106000
1*
#2124000
0*
#2142000
1*
#2146000
11
#2160000
0*
#2178000
b1 K
1*
#2196000
0*
#2214000
b11 9
b11 8
1=
1A
b11 K
1*
#2232000
0*
#2250000
b11 9
b11 8
0=
b100 7
0A
b11 D
b111 K
1*
#2268000
0*
#2286000
1*
#2304000
0*
#2322000
1*
#2340000
0*
#2358000
1*
#2368000
b100 O
01
#2376000
0*
#2394000
b110 K
1*
#2412000
0*
#2430000
1B
b100 K
1*
#2448000
0*
#2466000
0B
b11110000 M
b0 K
1*
#2484000
0*
#2502000
1$
1*
#2520000
0*
#2538000
1*
#2556000
0*
#2574000
1*
#2590000
b11010000 N
11
#2592000
0*
#2610000
b1 K
1*
#2628000
0*
#2646000
b100 9
b100 8
1=
1A
b11 K
1*
#2664000
0*
#2682000
b100 9
b100 8
0=
b101 7
0A
b100 D
b111 K
1*
#2700000
0*
#2718000
1*
#2736000
0*
#2754000
1*
#2772000
0*
#2790000
1*
#2808000
0*
#2812000
b11 O
01
#2826000
b110 K
1*
#2844000
0*
#2862000
1B
b100 K
1*
#2880000
0*
#2898000
0B
b11100000 M
b0 K
1*
#2916000
0*
#2934000
1*
#2952000
0*
#2970000
1*
#2988000
0*
#3006000
1*
#3024000
0*
#3034000
b11011000 N
11
#3042000
b1 K
1*
#3060000
0*
#3078000
b101 9
b101 8
1=
1A
b11 K
1*
#3096000
0*
#3114000
b101 9
b101 8
0=
b110 7
0A
b101 D
b111 K
1*
#3132000
0*
#3150000
1*
#3168000
0*
#3186000
1*
#3204000
0*
#3222000
1*
#3240000
0*
#3256000
b10 O
01
#3258000
b110 K
1*
#3276000
0*
#3294000
1B
b100 K
1*
#3312000
0*
#3330000
0B
b11000000 M
b0 K
1*
#3348000
0*
#3366000
1*
#3384000
0*
#3402000
1*
#3420000
0*
#3438000
1*
#3456000
0*
#3474000
1*
#3478000
b11011100 N
11
#3492000
0*
#3510000
b1 K
1*
#3528000
0*
#3546000
b110 9
b110 8
1=
1A
b11 K
1*
#3564000
0*
#3582000
b110 9
b110 8
0=
0A
b111 7
b111 K
b110 D
1*
#3600000
0*
#3618000
1*
#3636000
0*
#3654000
1*
#3672000
0*
#3690000
1*
#3700000
b1 O
01
#3708000
0*
#3726000
b110 K
1*
#3744000
0*
#3762000
1B
b100 K
1*
#3780000
0*
#3798000
0B
b0 K
b10000000 M
1*
#3816000
0*
#3834000
1*
#3852000
0*
#3870000
1*
#3888000
0*
#3906000
1*
#3922000
b11011110 N
11
#3924000
0*
#3942000
b1 K
1*
#3960000
0*
#3978000
b111 9
b111 8
1=
1A
b11 K
1*
#3996000
0*
#4014000
b111 9
b111 8
0=
0A
0#
06
b0 7
b111 K
b111 D
1*
#4032000
0*
#4050000
1*
#4068000
0*
#4086000
1*
#4104000
0*
#4122000
1*
#4140000
0*
#4144000
b0 O
01
#4158000
b110 K
1*
#4176000
0*
#4194000
1B
b100 K
1*
#4212000
0*
#4230000
0B
b0 K
b0 M
1*
#4248000
0*
#4266000
0$
1*
#4284000
0*
#4302000
1*
#4320000
0*
#4338000
1*
#4356000
0*
#4366000
11
#4374000
b1 K
1*
#4392000
0*
#4410000
b0 9
b0 8
1#
16
1=
1A
b11 K
1*
#4428000
0*
#4446000
b1 7
0=
0A
0#
06
b111 K
1G
b0 D
1E
b1 3
1*
#4464000
0*
#4482000
1?
b10101101 "
b10101101 >
b10101101 2
1F
0E
1%
0G
1*
#4500000
0*
#4518000
0?
0%
0F
b10101101 M
1*
#4536000
0*
#4554000
1$
1*
#4572000
0*
#4588000
b0 N
b1 4
b11011110 +
b111 O
01
#4590000
b110 K
1*
#4608000
0*
#4626000
1B
b100 K
1*
#4644000
0*
#4662000
0B
b0 K
1*
#4680000
0*
#4698000
1*
#4716000
0*
#4734000
1*
#4752000
0*
#4770000
1*
#4788000
0*
#4806000
1*
#4810000
b10000000 N
11
#4824000
0*
#4842000
b1 K
1*
#4860000
0*
#4878000
b1 9
b1 8
1=
1A
b11 K
1*
#4896000
0*
#4914000
b1 9
b1 8
0=
b10 7
0A
b1 D
b111 K
1*
#4932000
0*
#4950000
1*
#4968000
0*
#4986000
1*
#5004000
0*
#5022000
1*
#5032000
b110 O
01
#5040000
0*
#5058000
b110 K
1*
#5076000
0*
#5094000
1B
b100 K
1*
#5112000
0*
#5130000
0B
b1011010 M
b0 K
1*
#5148000
0*
#5166000
0$
1*
#5184000
0*
#5202000
1*
#5220000
0*
#5238000
1*
#5254000
11
#5256000
0*
#5274000
b1 K
1*
#5292000
0*
#5310000
b10 9
b10 8
1=
1A
b11 K
1*
#5328000
0*
#5346000
b10 9
b10 8
0=
b11 7
0A
b10 D
b111 K
1*
#5364000
0*
#5382000
1*
#5400000
0*
#5418000
1*
#5436000
0*
#5454000
1*
#5472000
0*
#5476000
b101 O
01
#5490000
b110 K
1*
#5508000
0*
#5526000
1B
b100 K
1*
#5544000
0*
#5562000
0B
b10110100 M
b0 K
1*
#5580000
0*
#5598000
1$
1*
#5616000
0*
#5634000
1*
#5652000
0*
#5670000
1*
#5688000
0*
#5698000
b10100000 N
11
#5706000
b1 K
1*
#5724000
0*
#5742000
b11 9
b11 8
1=
1A
b11 K
1*
#5760000
0*
#5778000
b11 9
b11 8
0=
b100 7
0A
b11 D
b111 K
1*
#5796000
0*
#5814000
1*
#5832000
0*
#5850000
1*
#5868000
0*
#5886000
1*
#5904000
0*
#5920000
b100 O
01
#5922000
b110 K
1*
#5940000
0*
#5958000
1B
b100 K
1*
#5976000
0*
#5994000
0B
b1101000 M
b0 K
1*
#6012000
0*
#6030000
0$
1*
#6048000
0*
#6066000
1*
#6084000
0*
#6102000
1*
#6120000
0*
#6138000
1*
#6142000
11
#6156000
0*
#6174000
b1 K
1*
#6192000
0*
#6210000
b100 9
b100 8
1=
1A
b11 K
1*
#6228000
0*
#6246000
b100 9
b100 8
0=
0A
b101 7
b111 K
b100 D
1*
#6264000
0*
#6282000
1*
#6300000
0*
#6318000
1*
#6336000
0*
#6354000
1*
#6364000
b11 O
01
#6372000
0*
#6390000
b110 K
1*
#6408000
0*
#6426000
1B
b100 K
1*
#6444000
0*
#6462000
0B
b0 K
b11010000 M
1*
#6480000
0*
#6498000
1$
1*
#6516000
0*
#6534000
1*
#6552000
0*
#6570000
1*
#6586000
b10101000 N
11
#6588000
0*
#6606000
b1 K
1*
#6624000
0*
#6642000
b101 9
b101 8
1=
1A
b11 K
1*
#6660000
0*
#6678000
b101 9
b101 8
0=
0A
b110 7
b111 K
b101 D
1*
#6696000
0*
#6714000
1*
#6732000
0*
#6750000
1*
#6768000
0*
#6786000
1*
#6804000
0*
#6808000
b10 O
01
#6822000
b110 K
1*
#6840000
0*
#6858000
1B
b100 K
1*
#6876000
0*
#6894000
0B
b0 K
b10100000 M
1*
#6912000
0*
#6930000
1*
#6948000
0*
#6966000
1*
#6984000
0*
#7002000
1*
#7020000
0*
#7030000
b10101100 N
11
#7038000
b1 K
1*
#7056000
0*
#7074000
b110 9
b110 8
1=
1A
b11 K
1*
#7092000
0*
#7110000
b110 9
b110 8
0=
0A
b111 7
b111 K
b110 D
1*
#7128000
0*
#7146000
1*
#7164000
0*
#7182000
1*
#7200000
0*
#7218000
1*
#7236000
0*
#7252000
b1 O
01
#7254000
b110 K
1*
#7272000
0*
#7290000
1B
b100 K
1*
#7308000
0*
#7326000
0B
b0 K
b1000000 M
1*
#7344000
0*
#7362000
0$
1*
#7380000
0*
#7398000
1*
#7416000
0*
#7434000
1*
#7452000
0*
#7470000
1*
#7474000
11
#7488000
0*
#7506000
b1 K
1*
#7524000
0*
#7542000
b111 9
b111 8
1=
1A
b11 K
1*
#7560000
0*
#7578000
b111 9
b111 8
0=
0#
06
b0 7
0A
b111 D
b111 K
1*
#7596000
0*
#7614000
1*
#7632000
0*
#7650000
1*
#7668000
0*
#7686000
1*
#7696000
b0 O
01
#7704000
0*
#7722000
b110 K
1*
#7740000
0*
#7758000
1B
b100 K
1*
#7776000
0*
#7794000
0B
b10000000 M
b0 K
1*
#7812000
0*
#7830000
1$
1*
#7848000
0*
#7866000
1*
#7884000
0*
#7902000
1*
#7918000
b10101101 N
11
#7920000
0*
#7938000
b1 K
1*
#7956000
0*
#7974000
b0 9
b0 8
1#
16
1=
1A
b11 K
1*
#7992000
0*
#8010000
b1 7
0=
0#
06
0A
b10 3
1E
1G
b0 D
b111 K
1*
#8028000
0*
#8046000
1?
0G
1%
1F
0E
b10111110 "
b10111110 >
b10111110 2
1*
#8064000
0*
#8082000
0?
b10111110 M
0F
0%
1*
#8100000
0*
#8118000
1*
#8136000
0*
#8140000
b0 N
b10 4
b10101101 +
b111 O
01
#8154000
b110 K
1*
#8172000
0*
#8190000
1B
b100 K
1*
#8208000
0*
#8226000
0B
b0 K
1*
#8244000
0*
#8262000
1*
#8280000
0*
#8298000
1*
#8316000
0*
#8334000
1*
#8352000
0*
#8362000
b10000000 N
11
#8370000
b1 K
1*
#8388000
0*
#8406000
b1 9
b1 8
1=
1A
b11 K
1*
#8424000
0*
#8442000
b1 9
b1 8
0=
b10 7
0A
b1 D
b111 K
1*
#8460000
0*
#8478000
1*
#8496000
0*
#8514000
1*
#8532000
0*
#8550000
1*
#8568000
0*
#8584000
b110 O
01
#8586000
b110 K
1*
#8604000
0*
#8622000
1B
b100 K
1*
#8640000
0*
#8658000
0B
b1111100 M
b0 K
1*
#8676000
0*
#8694000
0$
1*
#8712000
0*
#8730000
1*
#8748000
0*
#8766000
1*
#8784000
0*
#8802000
1*
#8806000
11
#8820000
0*
#8838000
b1 K
1*
#8856000
0*
#8874000
b10 9
b10 8
1=
1A
b11 K
1*
#8892000
0*
#8910000
b10 9
b10 8
0=
0A
b11 7
b111 K
b10 D
1*
#8928000
0*
#8946000
1*
#8964000
0*
#8982000
1*
#9000000
0*
#9018000
1*
#9028000
b101 O
01
#9036000
0*
#9054000
b110 K
1*
#9072000
0*
#9090000
1B
b100 K
1*
#9108000
0*
#9126000
0B
b0 K
b11111000 M
1*
#9144000
0*
#9162000
1$
1*
#9180000
0*
#9198000
1*
#9216000
0*
#9234000
1*
#9250000
b10100000 N
11
#9252000
0*
#9270000
b1 K
1*
#9288000
0*
#9306000
b11 9
b11 8
1=
1A
b11 K
1*
#9324000
0*
#9342000
b11 9
b11 8
0=
0A
b100 7
b111 K
b11 D
1*
#9360000
0*
#9378000
1*
#9396000
0*
#9414000
1*
#9432000
0*
#9450000
1*
#9468000
0*
#9472000
b100 O
01
#9486000
b110 K
1*
#9504000
0*
#9522000
1B
b100 K
1*
#9540000
0*
#9558000
0B
b0 K
b11110000 M
1*
#9576000
0*
#9594000
1*
#9612000
0*
#9630000
1*
#9648000
0*
#9666000
1*
#9684000
0*
#9694000
b10110000 N
11
#9702000
b1 K
1*
#9720000
0*
#9738000
b100 9
b100 8
1=
1A
b11 K
1*
#9756000
0*
#9774000
b100 9
b100 8
0=
0A
b101 7
b111 K
b100 D
1*
#9792000
0*
#9810000
1*
#9828000
0*
#9846000
1*
#9864000
0*
#9882000
1*
#9900000
0*
#9916000
b11 O
01
#9918000
b110 K
1*
#9936000
0*
#9954000
1B
b100 K
1*
#9972000
0*
#9990000
0B
b0 K
b11100000 M
1*
#10008000
0*
#10026000
1*
#10044000
0*
#10062000
1*
#10080000
0*
#10098000
1*
#10116000
0*
#10134000
1*
#10138000
b10111000 N
11
#10152000
0*
#10170000
b1 K
1*
#10188000
0*
#10206000
b101 9
b101 8
1=
1A
b11 K
1*
#10224000
0*
#10242000
b101 9
b101 8
0=
b110 7
0A
b101 D
b111 K
1*
#10260000
0*
#10278000
1*
#10296000
0*
#10314000
1*
#10332000
0*
#10350000
1*
#10360000
b10 O
01
#10368000
0*
#10386000
b110 K
1*
#10404000
0*
#10422000
1B
b100 K
1*
#10440000
0*
#10458000
0B
b11000000 M
b0 K
1*
#10476000
0*
#10494000
1*
#10512000
0*
#10530000
1*
#10548000
0*
#10566000
1*
#10582000
b10111100 N
11
#10584000
0*
#10602000
b1 K
1*
#10620000
0*
#10638000
b110 9
b110 8
1=
1A
b11 K
1*
#10656000
0*
#10674000
b110 9
b110 8
0=
b111 7
0A
b110 D
b111 K
1*
#10692000
0*
#10710000
1*
#10728000
0*
#10746000
1*
#10764000
0*
#10782000
1*
#10800000
0*
#10804000
b1 O
01
#10818000
b110 K
1*
#10836000
0*
#10854000
1B
b100 K
1*
#10872000
0*
#10890000
0B
b10000000 M
b0 K
1*
#10908000
0*
#10926000
1*
#10944000
0*
#10962000
1*
#10980000
0*
#10998000
1*
#11016000
0*
#11026000
b10111110 N
11
#11034000
b1 K
1*
#11052000
0*
#11070000
b111 9
b111 8
1=
1A
b11 K
1*
#11088000
0*
#11106000
b111 9
b111 8
0=
0#
06
b0 7
0A
b111 D
b111 K
1*
#11124000
0*
#11142000
1*
#11160000
0*
#11178000
1*
#11196000
0*
#11214000
1*
#11232000
0*
#11248000
b0 O
01
#11250000
b110 K
1*
#11268000
0*
#11286000
1B
b100 K
1*
#11304000
0*
#11322000
0B
b0 M
b0 K
1*
#11340000
0*
#11358000
0$
1*
#11376000
0*
#11394000
1*
#11412000
0*
#11430000
1*
#11448000
0*
#11466000
1*
#11470000
11
#11484000
0*
#11502000
b1 K
1*
#11520000
0*
#11538000
b0 9
b0 8
1#
16
1=
1A
b11 K
1*
#11556000
0*
#11574000
b1 7
0=
0A
0#
06
b111 K
1G
b0 D
1E
b11 3
1*
#11592000
0*
#11610000
1?
b11101111 "
b11101111 >
b11101111 2
1F
0E
1%
0G
1*
#11628000
0*
#11646000
0?
0%
0F
b11101111 M
1*
#11664000
0*
#11682000
1$
1*
#11692000
b0 N
b11 4
b10111110 +
b111 O
01
#11700000
0*
#11718000
b110 K
1*
#11736000
0*
#11754000
1B
b100 K
1*
#11772000
0*
#11790000
0B
b0 K
1*
#11808000
0*
#11826000
1*
#11844000
0*
#11862000
1*
#11880000
0*
#11898000
1*
#11914000
b10000000 N
11
#11916000
0*
#11934000
b1 K
1*
#11952000
0*
#11970000
b1 9
b1 8
1=
1A
b11 K
1*
#11988000
0*
#12006000
b1 9
b1 8
0=
0A
b10 7
b111 K
b1 D
1*
#12024000
0*
#12042000
1*
